{"hourlyDataList":[{"moveHourly":true,"startTime":1745283600000},{"moveHourly":true,"startTime":1745287200000},{"moveHourly":true,"startTime":1745290800000},{"moveHourly":true,"startTime":1745294400000},{"moveHourly":true,"startTime":1745298000000},{"moveHourly":true,"startTime":1745301600000},{"moveHourly":true,"startTime":1745305200000},{"moveHourly":true,"startTime":1745308800000},{"moveHourly":true,"startTime":1745316000000},{"moveHourly":true,"startTime":1745319600000},{"moveHourly":true,"startTime":1745323200000},{"moveHourly":true,"startTime":1745330400000},{"moveHourly":true,"startTime":1745337600000},{"moveHourly":true,"startTime":1745341200000},{"moveHourly":true,"startTime":1745344800000},{"moveHourly":true,"startTime":1745352000000},{"moveHourly":true,"startTime":1745355600000},{"moveHourly":true,"startTime":1745359200000},{"moveHourly":true,"startTime":1745362800000}],"mActivityList":[{"mActiveTime":2135294,"mActiveTimeType":0,"mCalorie":351.073,"mCategory":200,"mDetailInfoId":"7f658c56-2e2e-4f1c-9906-dc9ac6701546","mDistance":2935.132,"mDuration":4005068,"mEndTime":28884523,"mStartTime":24879455,"mType":1001},{"mActiveTime":666044,"mActiveTimeType":0,"mCalorie":69.0,"mCategory":204,"mDetailInfoId":"2b6a59d6-7540-414d-a1eb-53cbf21ff2c2","mDistance":934.03,"mDuration":666044,"mEndTime":41241176,"mStartTime":40575132,"mType":1001},{"mActiveTime":312641,"mActiveTimeType":0,"mCalorie":56.069946,"mCategory":200,"mDetailInfoId":"060945af-5808-4f1a-9455-96829123797f","mDistance":432.48584,"mDuration":312641,"mEndTime":86400000,"mStartTime":86087359,"mType":1001}],"mAdaptiveGoal":0,"mIsGoalAchieved":false,"mIsMostActiveAchieved":false,"mMostActiveMinutes":0,"mStreakDayCount":0,"mUnitDataList":[{"distance":38.269997,"dynamicActiveTime":0,"exerciseCalorie":0.0,"exerciseTime":0,"floorCount":0,"mCalorie":1.61,"mOthersTime":0,"mRunTime":0,"mStartTime":6000000,"mTimeUnit":600000,"mWalkTime":34017,"runStep":0,"walkStep":51},{"distance":4.91,"dynamicActiveTime":0,"exerciseCalorie":0.0,"exerciseTime":0,"floorCount":0,"mCalorie":0.19,"mOthersTime":0,"mRunTime":0,"mStartTime":9000000,"mTimeUnit":600000,"mWalkTime":4002,"runStep":0,"walkStep":6},{"distance":9.05,"dynamicActiveTime":0,"exerciseCalorie":0.0,"exerciseTime":0,"floorCount":0,"mCalorie":0.44,"mOthersTime":0,"mRunTime":0,"mStartTime":9600000,"mTimeUnit":600000,"mWalkTime":7337,"runStep":0,"walkStep":11},{"distance":8.28,"dynamicActiveTime":0,"exerciseCalorie":0.0,"exerciseTime":0,"floorCount":0,"mCalorie":0.41,"mOthersTime":0,"mRunTime":0,"mStartTime":10200000,"mTimeUnit":600000,"mWalkTime":6670,"runStep":0,"walkStep":10},{"distance":82.44,"dynamicActiveTime":0,"exerciseCalorie":0.0,"exerciseTime":0,"floorCount":0,"mCalorie":3.84,"mOthersTime":0,"mRunTime":0,"mStartTime":10800000,"mTimeUnit":600000,"mWalkTime":68701,"runStep":0,"walkStep":103},{"distance":19.88,"dynamicActiveTime":0,"exerciseCalorie":0.0,"exerciseTime":0,"floorCount":0,"mCalorie":0.78,"mOthersTime":0,"mRunTime":0,"mStartTime":16800000,"mTimeUnit":600000,"mWalkTime":16675,"runStep":0,"walkStep":25},{"distance":40.44,"dynamicActiveTime":0,"exerciseCalorie":0.0,"exerciseTime":0,"floorCount":0,"mCalorie":2.3,"mOthersTime":0,"mRunTime":0,"mStartTime":17400000,"mTimeUnit":600000,"mWalkTime":29348,"runStep":0,"walkStep":44},{"distance":25.27,"dynamicActiveTime":0,"exerciseCalorie":0.0,"exerciseTime":0,"floorCount":0,"mCalorie":1.08,"mOthersTime":0,"mRunTime":0,"mStartTime":18000000,"mTimeUnit":600000,"mWalkTime":22678,"runStep":0,"walkStep":34},{"distance":92.509995,"dynamicActiveTime":0,"exerciseCalorie":0.0,"exerciseTime":0,"floorCount":0,"mCalorie":4.1,"mOthersTime":0,"mRunTime":0,"mStartTime":18600000,"mTimeUnit":600000,"mWalkTime":80040,"runStep":0,"walkStep":120},{"distance":95.380005,"dynamicActiveTime":0,"exerciseCalorie":0.0,"exerciseTime":0,"floorCount":0,"mCalorie":4.4399996,"mOthersTime":0,"mRunTime":400,"mStartTime":19200000,"mTimeUnit":600000,"mWalkTime":78039,"runStep":1,"walkStep":117},{"distance":19.97,"dynamicActiveTime":0,"exerciseCalorie":0.0,"exerciseTime":0,"floorCount":0,"mCalorie":0.98,"mOthersTime":0,"mRunTime":0,"mStartTime":19800000,"mTimeUnit":600000,"mWalkTime":16008,"runStep":0,"walkStep":24},{"distance":136.15,"dynamicActiveTime":0,"exerciseCalorie":0.0,"exerciseTime":0,"floorCount":0,"mCalorie":6.0599995,"mOthersTime":0,"mRunTime":0,"mStartTime":20400000,"mTimeUnit":600000,"mWalkTime":104689,"runStep":0,"walkStep":167},{"distance":52.73,"dynamicActiveTime":0,"exerciseCalorie":0.0,"exerciseTime":0,"floorCount":0,"mCalorie":4.93,"mOthersTime":0,"mRunTime":0,"mStartTime":21600000,"mTimeUnit":600000,"mWalkTime":41354,"runStep":0,"walkStep":62},{"distance":123.159996,"dynamicActiveTime":0,"exerciseCalorie":0.0,"exerciseTime":0,"floorCount":0,"mCalorie":5.9599996,"mOthersTime":0,"mRunTime":0,"mStartTime":22200000,"mTimeUnit":600000,"mWalkTime":97382,"runStep":0,"walkStep":146},{"distance":624.9557,"dynamicActiveTime":330000,"exerciseCalorie":28.098074,"exerciseTime":320545,"floorCount":0,"mCalorie":62.133575,"mOthersTime":0,"mRunTime":6793,"mStartTime":24600000,"mTimeUnit":600000,"mWalkTime":432148,"runStep":25,"walkStep":826},{"distance":824.7479,"dynamicActiveTime":600000,"exerciseCalorie":52.59431,"exerciseTime":600000,"floorCount":0,"mCalorie":98.64862,"mOthersTime":0,"mRunTime":0,"mStartTime":25200000,"mTimeUnit":600000,"mWalkTime":600000,"runStep":2,"walkStep":1146},{"distance":824.7479,"dynamicActiveTime":560000,"exerciseCalorie":52.59431,"exerciseTime":600000,"floorCount":0,"mCalorie":98.64862,"mOthersTime":0,"mRunTime":0,"mStartTime":25800000,"mTimeUnit":600000,"mWalkTime":600000,"runStep":0,"walkStep":997},{"distance":824.7479,"dynamicActiveTime":200000,"exerciseCalorie":52.59431,"exerciseTime":600000,"floorCount":0,"mCalorie":98.64862,"mOthersTime":0,"mRunTime":0,"mStartTime":26400000,"mTimeUnit":600000,"mWalkTime":600000,"runStep":3,"walkStep":283},{"distance":20.273678,"dynamicActiveTime":90000,"exerciseCalorie":52.59431,"exerciseTime":14749,"floorCount":0,"mCalorie":2.4249475,"mOthersTime":0,"mRunTime":0,"mStartTime":27000000,"mTimeUnit":600000,"mWalkTime":14749,"runStep":15,"walkStep":304},{"distance":0.0,"dynamicActiveTime":90000,"exerciseCalorie":52.59431,"exerciseTime":0,"floorCount":0,"mCalorie":0.0,"mOthersTime":0,"mRunTime":0,"mStartTime":27600000,"mTimeUnit":600000,"mWalkTime":0,"runStep":32,"walkStep":357},{"distance":0.0,"dynamicActiveTime":0,"exerciseCalorie":52.59431,"exerciseTime":0,"floorCount":0,"mCalorie":0.0,"mOthersTime":0,"mRunTime":0,"mStartTime":28200000,"mTimeUnit":600000,"mWalkTime":0,"runStep":0,"walkStep":0},{"distance":77.188065,"dynamicActiveTime":0,"exerciseCalorie":7.4090486,"exerciseTime":0,"floorCount":0,"mCalorie":4.2592926,"mOthersTime":0,"mRunTime":0,"mStartTime":28800000,"mTimeUnit":600000,"mWalkTime":64762,"runStep":0,"walkStep":112},{"distance":78.78999,"dynamicActiveTime":0,"exerciseCalorie":0.0,"exerciseTime":0,"floorCount":0,"mCalorie":3.8,"mOthersTime":0,"mRunTime":0,"mStartTime":29400000,"mTimeUnit":600000,"mWalkTime":63365,"runStep":0,"walkStep":95},{"distance":394.22,"dynamicActiveTime":0,"exerciseCalorie":0.0,"exerciseTime":0,"floorCount":0,"mCalorie":19.289999,"mOthersTime":0,"mRunTime":400,"mStartTime":36000000,"mTimeUnit":600000,"mWalkTime":287417,"runStep":1,"walkStep":464},{"distance":84.020004,"dynamicActiveTime":0,"exerciseCalorie":0.0,"exerciseTime":0,"floorCount":0,"mCalorie":4.04,"mOthersTime":0,"mRunTime":400,"mStartTime":36600000,"mTimeUnit":600000,"mWalkTime":66033,"runStep":1,"walkStep":99},{"distance":499.46997,"dynamicActiveTime":0,"exerciseCalorie":0.0,"exerciseTime":0,"floorCount":0,"mCalorie":24.080002,"mOthersTime":0,"mRunTime":0,"mStartTime":37200000,"mTimeUnit":600000,"mWalkTime":362698,"runStep":0,"walkStep":607},{"distance":28.560001,"dynamicActiveTime":0,"exerciseCalorie":0.0,"exerciseTime":0,"floorCount":0,"mCalorie":1.44,"mOthersTime":0,"mRunTime":0,"mStartTime":38400000,"mTimeUnit":600000,"mWalkTime":24012,"runStep":0,"walkStep":36},{"distance":12.55,"dynamicActiveTime":0,"exerciseCalorie":0.0,"exerciseTime":0,"floorCount":0,"mCalorie":0.67,"mOthersTime":0,"mRunTime":0,"mStartTime":39000000,"mTimeUnit":600000,"mWalkTime":10672,"runStep":0,"walkStep":16},{"distance":323.63455,"dynamicActiveTime":60000,"exerciseCalorie":23.295595,"exerciseTime":224868,"floorCount":0,"mCalorie":23.686506,"mOthersTime":0,"mRunTime":0,"mStartTime":40200000,"mTimeUnit":600000,"mWalkTime":231428,"runStep":0,"walkStep":358},{"distance":708.7165,"dynamicActiveTime":480000,"exerciseCalorie":45.704403,"exerciseTime":441176,"floorCount":0,"mCalorie":49.279114,"mOthersTime":0,"mRunTime":0,"mStartTime":40800000,"mTimeUnit":600000,"mWalkTime":505923,"runStep":0,"walkStep":913},{"distance":492.13992,"dynamicActiveTime":0,"exerciseCalorie":0.0,"exerciseTime":0,"floorCount":0,"mCalorie":19.999996,"mOthersTime":0,"mRunTime":0,"mStartTime":41400000,"mTimeUnit":600000,"mWalkTime":340687,"runStep":0,"walkStep":627},{"distance":63.880005,"dynamicActiveTime":0,"exerciseCalorie":0.0,"exerciseTime":0,"floorCount":0,"mCalorie":2.7799993,"mOthersTime":0,"mRunTime":0,"mStartTime":42000000,"mTimeUnit":600000,"mWalkTime":54027,"runStep":0,"walkStep":81},{"distance":40.320004,"dynamicActiveTime":0,"exerciseCalorie":0.0,"exerciseTime":0,"floorCount":0,"mCalorie":2.05,"mOthersTime":0,"mRunTime":800,"mStartTime":42600000,"mTimeUnit":600000,"mWalkTime":30015,"runStep":2,"walkStep":45},{"distance":136.59001,"dynamicActiveTime":0,"exerciseCalorie":0.0,"exerciseTime":0,"floorCount":0,"mCalorie":7.639999,"mOthersTime":0,"mRunTime":4800,"mStartTime":45000000,"mTimeUnit":600000,"mWalkTime":100050,"runStep":12,"walkStep":150},{"distance":18.0,"dynamicActiveTime":0,"exerciseCalorie":0.0,"exerciseTime":0,"floorCount":0,"mCalorie":0.84,"mOthersTime":0,"mRunTime":0,"mStartTime":45600000,"mTimeUnit":600000,"mWalkTime":14674,"runStep":0,"walkStep":22},{"distance":35.3,"dynamicActiveTime":0,"exerciseCalorie":0.0,"exerciseTime":0,"floorCount":0,"mCalorie":1.74,"mOthersTime":0,"mRunTime":0,"mStartTime":52800000,"mTimeUnit":600000,"mWalkTime":28681,"runStep":0,"walkStep":43},{"distance":8.03,"dynamicActiveTime":0,"exerciseCalorie":0.0,"exerciseTime":0,"floorCount":0,"mCalorie":0.42,"mOthersTime":0,"mRunTime":0,"mStartTime":54600000,"mTimeUnit":600000,"mWalkTime":6670,"runStep":0,"walkStep":10},{"distance":121.4,"dynamicActiveTime":0,"exerciseCalorie":0.0,"exerciseTime":0,"floorCount":0,"mCalorie":6.5199995,"mOthersTime":0,"mRunTime":0,"mStartTime":58200000,"mTimeUnit":600000,"mWalkTime":98049,"runStep":0,"walkStep":147},{"distance":150.62,"dynamicActiveTime":0,"exerciseCalorie":0.0,"exerciseTime":0,"floorCount":0,"mCalorie":6.8399997,"mOthersTime":0,"mRunTime":0,"mStartTime":58800000,"mTimeUnit":600000,"mWalkTime":122061,"runStep":0,"walkStep":183},{"distance":248.04,"dynamicActiveTime":0,"exerciseCalorie":0.0,"exerciseTime":0,"floorCount":0,"mCalorie":12.31,"mOthersTime":0,"mRunTime":6800,"mStartTime":60000000,"mTimeUnit":600000,"mWalkTime":196765,"runStep":17,"walkStep":295},{"distance":38.19,"dynamicActiveTime":0,"exerciseCalorie":0.0,"exerciseTime":0,"floorCount":0,"mCalorie":1.6099997,"mOthersTime":0,"mRunTime":0,"mStartTime":60600000,"mTimeUnit":600000,"mWalkTime":33350,"runStep":0,"walkStep":50},{"distance":10.21,"dynamicActiveTime":0,"exerciseCalorie":0.0,"exerciseTime":0,"floorCount":0,"mCalorie":0.41,"mOthersTime":0,"mRunTime":0,"mStartTime":61800000,"mTimeUnit":600000,"mWalkTime":7337,"runStep":0,"walkStep":11},{"distance":45.18,"dynamicActiveTime":0,"exerciseCalorie":0.0,"exerciseTime":0,"floorCount":0,"mCalorie":2.19,"mOthersTime":0,"mRunTime":0,"mStartTime":63000000,"mTimeUnit":600000,"mWalkTime":38686,"runStep":0,"walkStep":58},{"distance":32.17,"dynamicActiveTime":0,"exerciseCalorie":0.0,"exerciseTime":0,"floorCount":0,"mCalorie":1.55,"mOthersTime":0,"mRunTime":0,"mStartTime":63600000,"mTimeUnit":600000,"mWalkTime":26013,"runStep":0,"walkStep":39},{"distance":323.62,"dynamicActiveTime":0,"exerciseCalorie":0.0,"exerciseTime":0,"floorCount":0,"mCalorie":14.329999,"mOthersTime":0,"mRunTime":0,"mStartTime":64200000,"mTimeUnit":600000,"mWalkTime":280807,"runStep":0,"walkStep":421},{"distance":199.33,"dynamicActiveTime":0,"exerciseCalorie":0.0,"exerciseTime":0,"floorCount":0,"mCalorie":8.799999,"mOthersTime":0,"mRunTime":0,"mStartTime":64800000,"mTimeUnit":600000,"mWalkTime":167417,"runStep":0,"walkStep":251},{"distance":97.759995,"dynamicActiveTime":0,"exerciseCalorie":0.0,"exerciseTime":0,"floorCount":0,"mCalorie":4.3199997,"mOthersTime":0,"mRunTime":0,"mStartTime":65400000,"mTimeUnit":600000,"mWalkTime":80707,"runStep":0,"walkStep":121},{"distance":95.200005,"dynamicActiveTime":0,"exerciseCalorie":0.0,"exerciseTime":0,"floorCount":0,"mCalorie":4.15,"mOthersTime":0,"mRunTime":0,"mStartTime":66000000,"mTimeUnit":600000,"mWalkTime":79373,"runStep":0,"walkStep":119},{"distance":25.38,"dynamicActiveTime":0,"exerciseCalorie":0.0,"exerciseTime":0,"floorCount":0,"mCalorie":1.01,"mOthersTime":0,"mRunTime":0,"mStartTime":66600000,"mTimeUnit":600000,"mWalkTime":22011,"runStep":0,"walkStep":33},{"distance":32.27,"dynamicActiveTime":0,"exerciseCalorie":0.0,"exerciseTime":0,"floorCount":0,"mCalorie":1.74,"mOthersTime":0,"mRunTime":0,"mStartTime":67200000,"mTimeUnit":600000,"mWalkTime":26680,"runStep":0,"walkStep":40},{"distance":45.21,"dynamicActiveTime":0,"exerciseCalorie":0.0,"exerciseTime":0,"floorCount":0,"mCalorie":2.24,"mOthersTime":0,"mRunTime":0,"mStartTime":67800000,"mTimeUnit":600000,"mWalkTime":36685,"runStep":0,"walkStep":55},{"distance":210.34999,"dynamicActiveTime":0,"exerciseCalorie":0.0,"exerciseTime":0,"floorCount":0,"mCalorie":9.27,"mOthersTime":0,"mRunTime":400,"mStartTime":74400000,"mTimeUnit":600000,"mWalkTime":152016,"runStep":1,"walkStep":261},{"distance":134.79001,"dynamicActiveTime":0,"exerciseCalorie":0.0,"exerciseTime":0,"floorCount":0,"mCalorie":6.3599997,"mOthersTime":0,"mRunTime":0,"mStartTime":75000000,"mTimeUnit":600000,"mWalkTime":105356,"runStep":0,"walkStep":166},{"distance":160.53001,"dynamicActiveTime":0,"exerciseCalorie":0.0,"exerciseTime":0,"floorCount":0,"mCalorie":7.87,"mOthersTime":0,"mRunTime":0,"mStartTime":75600000,"mTimeUnit":600000,"mWalkTime":130065,"runStep":0,"walkStep":195},{"distance":189.31001,"dynamicActiveTime":0,"exerciseCalorie":0.0,"exerciseTime":0,"floorCount":0,"mCalorie":7.9700003,"mOthersTime":0,"mRunTime":400,"mStartTime":76200000,"mTimeUnit":600000,"mWalkTime":142041,"runStep":1,"walkStep":236},{"distance":56.95,"dynamicActiveTime":0,"exerciseCalorie":0.0,"exerciseTime":0,"floorCount":0,"mCalorie":2.69,"mOthersTime":0,"mRunTime":0,"mStartTime":76800000,"mTimeUnit":600000,"mWalkTime":46023,"runStep":0,"walkStep":69},{"distance":266.47998,"dynamicActiveTime":0,"exerciseCalorie":0.0,"exerciseTime":0,"floorCount":0,"mCalorie":13.07,"mOthersTime":0,"mRunTime":0,"mStartTime":77400000,"mTimeUnit":600000,"mWalkTime":202738,"runStep":0,"walkStep":320},{"distance":191.34,"dynamicActiveTime":0,"exerciseCalorie":0.0,"exerciseTime":0,"floorCount":0,"mCalorie":9.42,"mOthersTime":0,"mRunTime":0,"mStartTime":78000000,"mTimeUnit":600000,"mWalkTime":150742,"runStep":0,"walkStep":226},{"distance":184.63998,"dynamicActiveTime":0,"exerciseCalorie":0.0,"exerciseTime":0,"floorCount":0,"mCalorie":8.459998,"mOthersTime":0,"mRunTime":1600,"mStartTime":78600000,"mTimeUnit":600000,"mWalkTime":150045,"runStep":4,"walkStep":226},{"distance":20.15,"dynamicActiveTime":0,"exerciseCalorie":0.0,"exerciseTime":0,"floorCount":0,"mCalorie":0.79,"mOthersTime":0,"mRunTime":0,"mStartTime":79200000,"mTimeUnit":600000,"mWalkTime":18009,"runStep":0,"walkStep":27},{"distance":132.67,"dynamicActiveTime":0,"exerciseCalorie":0.0,"exerciseTime":0,"floorCount":0,"mCalorie":6.3599997,"mOthersTime":0,"mRunTime":0,"mStartTime":79800000,"mTimeUnit":600000,"mWalkTime":108721,"runStep":0,"walkStep":163},{"distance":432.48584,"dynamicActiveTime":0,"exerciseCalorie":56.069946,"exerciseTime":312641,"floorCount":0,"mCalorie":56.069946,"mOthersTime":0,"mRunTime":0,"mStartTime":85800000,"mTimeUnit":600000,"mWalkTime":312641,"runStep":0,"walkStep":0}],"version":1}