[{"elapsed_time":604280,"interval":1,"segment":1,"source_type":4,"start_time":1705846472946},{"elapsed_time":605179,"interval":1,"segment":1,"source_type":4,"start_time":1705846473845},{"elapsed_time":606179,"interval":1,"segment":1,"source_type":4,"start_time":1705846474845},{"elapsed_time":607179,"interval":1,"segment":1,"source_type":4,"start_time":1705846475845},{"elapsed_time":608179,"interval":1,"segment":1,"source_type":4,"start_time":1705846476845},{"elapsed_time":609179,"interval":1,"segment":1,"source_type":4,"start_time":1705846477845},{"elapsed_time":610179,"interval":1,"segment":1,"source_type":4,"start_time":1705846478845},{"elapsed_time":611179,"interval":1,"segment":1,"source_type":4,"start_time":1705846479845},{"elapsed_time":612179,"interval":1,"segment":1,"source_type":4,"start_time":1705846480845},{"elapsed_time":613183,"interval":1,"segment":1,"source_type":4,"start_time":1705846481849},{"elapsed_time":614301,"interval":1,"segment":1,"source_type":4,"start_time":1705846482967},{"elapsed_time":615301,"interval":1,"segment":1,"source_type":4,"start_time":1705846483967},{"elapsed_time":616301,"interval":1,"segment":1,"source_type":4,"start_time":1705846484967},{"elapsed_time":617301,"interval":1,"segment":1,"source_type":4,"start_time":1705846485967},{"elapsed_time":618301,"interval":1,"segment":1,"source_type":4,"start_time":1705846486967},{"elapsed_time":619301,"interval":1,"segment":1,"source_type":4,"start_time":1705846487967},{"elapsed_time":620301,"interval":1,"segment":1,"source_type":4,"start_time":1705846488967},{"elapsed_time":621301,"interval":1,"segment":1,"source_type":4,"start_time":1705846489967},{"elapsed_time":622301,"interval":1,"segment":1,"source_type":4,"start_time":1705846490967},{"elapsed_time":623301,"interval":1,"segment":1,"source_type":4,"start_time":1705846491967},{"elapsed_time":624301,"interval":1,"segment":1,"source_type":4,"start_time":1705846492967},{"elapsed_time":625404,"interval":1,"segment":1,"source_type":4,"start_time":1705846494070},{"elapsed_time":626593,"interval":1,"segment":1,"source_type":4,"start_time":1705846495259},{"elapsed_time":627593,"interval":1,"segment":1,"source_type":4,"start_time":1705846496259},{"elapsed_time":628593,"interval":1,"segment":1,"source_type":4,"start_time":1705846497259},{"elapsed_time":629593,"interval":1,"segment":1,"source_type":4,"start_time":1705846498259},{"elapsed_time":630595,"interval":1,"segment":1,"source_type":4,"start_time":1705846499261},{"elapsed_time":631598,"interval":1,"segment":1,"source_type":4,"start_time":1705846500264},{"elapsed_time":632481,"interval":1,"segment":1,"source_type":4,"start_time":1705846501147},{"elapsed_time":633438,"interval":1,"segment":1,"source_type":4,"start_time":1705846502104},{"elapsed_time":634166,"interval":1,"segment":1,"source_type":4,"start_time":1705846502832},{"elapsed_time":635166,"interval":1,"segment":1,"source_type":4,"start_time":1705846503832},{"elapsed_time":636166,"interval":1,"segment":1,"source_type":4,"start_time":1705846504832},{"elapsed_time":637246,"interval":1,"segment":1,"source_type":4,"start_time":1705846505912},{"elapsed_time":638246,"interval":1,"segment":1,"source_type":4,"start_time":1705846506912},{"elapsed_time":639246,"interval":1,"segment":1,"source_type":4,"start_time":1705846507912},{"elapsed_time":640246,"interval":1,"segment":1,"source_type":4,"start_time":1705846508912},{"elapsed_time":641246,"interval":1,"segment":1,"source_type":4,"start_time":1705846509912},{"elapsed_time":642246,"interval":1,"segment":1,"source_type":4,"start_time":1705846510912},{"elapsed_time":643246,"interval":1,"segment":1,"source_type":4,"start_time":1705846511912},{"elapsed_time":644350,"interval":1,"segment":1,"source_type":4,"start_time":1705846513016},{"elapsed_time":645799,"interval":1,"segment":1,"source_type":4,"start_time":1705846514465},{"elapsed_time":646799,"interval":1,"segment":1,"source_type":4,"start_time":1705846515465},{"elapsed_time":647799,"interval":1,"segment":1,"source_type":4,"start_time":1705846516465},{"elapsed_time":648799,"interval":1,"segment":1,"source_type":4,"start_time":1705846517465},{"elapsed_time":649799,"interval":1,"segment":1,"source_type":4,"start_time":1705846518465},{"elapsed_time":650799,"interval":1,"segment":1,"source_type":4,"start_time":1705846519465},{"elapsed_time":651799,"interval":1,"segment":1,"source_type":4,"start_time":1705846520465},{"elapsed_time":652799,"interval":1,"segment":1,"source_type":4,"start_time":1705846521465},{"elapsed_time":653799,"interval":1,"segment":1,"source_type":4,"start_time":1705846522465},{"elapsed_time":654799,"interval":1,"segment":1,"source_type":4,"start_time":1705846523465},{"elapsed_time":655799,"interval":1,"segment":1,"source_type":4,"start_time":1705846524465},{"elapsed_time":656799,"interval":1,"segment":1,"source_type":4,"start_time":1705846525465},{"elapsed_time":657799,"interval":1,"segment":1,"source_type":4,"start_time":1705846526465},{"elapsed_time":658799,"interval":1,"segment":1,"source_type":4,"start_time":1705846527465},{"elapsed_time":659799,"interval":1,"segment":1,"source_type":4,"start_time":1705846528465},{"elapsed_time":660799,"interval":1,"segment":1,"source_type":4,"start_time":1705846529465},{"elapsed_time":661799,"interval":1,"segment":1,"source_type":4,"start_time":1705846530465},{"elapsed_time":662799,"interval":1,"segment":1,"source_type":4,"start_time":1705846531465},{"elapsed_time":663799,"interval":1,"segment":1,"source_type":4,"start_time":1705846532465},{"elapsed_time":664799,"interval":1,"segment":1,"source_type":4,"start_time":1705846533465},{"elapsed_time":665799,"interval":1,"segment":1,"source_type":4,"start_time":1705846534465},{"elapsed_time":666799,"interval":1,"segment":1,"source_type":4,"start_time":1705846535465},{"elapsed_time":667799,"interval":1,"segment":1,"source_type":4,"start_time":1705846536465},{"elapsed_time":668799,"interval":1,"segment":1,"source_type":4,"start_time":1705846537465},{"elapsed_time":669799,"interval":1,"segment":1,"source_type":4,"start_time":1705846538465},{"elapsed_time":670799,"interval":1,"segment":1,"source_type":4,"start_time":1705846539465},{"elapsed_time":671799,"interval":1,"segment":1,"source_type":4,"start_time":1705846540465},{"elapsed_time":672799,"interval":1,"segment":1,"source_type":4,"start_time":1705846541465},{"elapsed_time":673799,"interval":1,"segment":1,"source_type":4,"start_time":1705846542465},{"elapsed_time":674799,"interval":1,"segment":1,"source_type":4,"start_time":1705846543465},{"elapsed_time":675799,"interval":1,"segment":1,"source_type":4,"start_time":1705846544465},{"elapsed_time":676799,"interval":1,"segment":1,"source_type":4,"start_time":1705846545465},{"elapsed_time":677799,"interval":1,"segment":1,"source_type":4,"start_time":1705846546465},{"elapsed_time":678799,"interval":1,"segment":1,"source_type":4,"start_time":1705846547465},{"elapsed_time":679799,"interval":1,"segment":1,"source_type":4,"start_time":1705846548465},{"elapsed_time":680799,"interval":1,"segment":1,"source_type":4,"start_time":1705846549465},{"elapsed_time":681685,"interval":1,"segment":1,"source_type":4,"start_time":1705846550351},{"elapsed_time":682685,"interval":1,"segment":1,"source_type":4,"start_time":1705846551351},{"elapsed_time":683685,"interval":1,"segment":1,"source_type":4,"start_time":1705846552351},{"elapsed_time":684685,"interval":1,"segment":1,"source_type":4,"start_time":1705846553351},{"elapsed_time":685685,"interval":1,"segment":1,"source_type":4,"start_time":1705846554351},{"elapsed_time":686685,"interval":1,"segment":1,"source_type":4,"start_time":1705846555351},{"elapsed_time":687685,"interval":1,"segment":1,"source_type":4,"start_time":1705846556351},{"elapsed_time":688685,"interval":1,"segment":1,"source_type":4,"start_time":1705846557351},{"elapsed_time":689685,"interval":1,"segment":1,"source_type":4,"start_time":1705846558351},{"elapsed_time":690685,"interval":1,"segment":1,"source_type":4,"start_time":1705846559351},{"elapsed_time":691685,"interval":1,"segment":1,"source_type":4,"start_time":1705846560351},{"elapsed_time":692685,"interval":1,"segment":1,"source_type":4,"start_time":1705846561351},{"elapsed_time":693685,"interval":1,"segment":1,"source_type":4,"start_time":1705846562351},{"elapsed_time":694685,"interval":1,"segment":1,"source_type":4,"start_time":1705846563351},{"elapsed_time":695685,"interval":1,"segment":1,"source_type":4,"start_time":1705846564351},{"elapsed_time":696685,"interval":1,"segment":1,"source_type":4,"start_time":1705846565351},{"elapsed_time":697685,"interval":1,"segment":1,"source_type":4,"start_time":1705846566351},{"elapsed_time":698685,"interval":1,"segment":1,"source_type":4,"start_time":1705846567351},{"elapsed_time":699685,"interval":1,"segment":1,"source_type":4,"start_time":1705846568351},{"elapsed_time":700685,"interval":1,"segment":1,"source_type":4,"start_time":1705846569351},{"elapsed_time":701685,"interval":1,"segment":1,"source_type":4,"start_time":1705846570351},{"elapsed_time":702685,"interval":1,"segment":1,"source_type":4,"start_time":1705846571351},{"elapsed_time":703685,"interval":1,"segment":1,"source_type":4,"start_time":1705846572351},{"elapsed_time":704685,"interval":1,"segment":1,"source_type":4,"start_time":1705846573351},{"elapsed_time":705685,"interval":1,"segment":1,"source_type":4,"start_time":1705846574351},{"elapsed_time":706685,"interval":1,"segment":1,"source_type":4,"start_time":1705846575351},{"elapsed_time":707685,"interval":1,"segment":1,"source_type":4,"start_time":1705846576351},{"elapsed_time":708685,"interval":1,"segment":1,"source_type":4,"start_time":1705846577351},{"elapsed_time":709685,"interval":1,"segment":1,"source_type":4,"start_time":1705846578351},{"elapsed_time":710685,"interval":1,"segment":1,"source_type":4,"start_time":1705846579351},{"elapsed_time":711685,"interval":1,"segment":1,"source_type":4,"start_time":1705846580351},{"elapsed_time":712685,"interval":1,"segment":1,"source_type":4,"start_time":1705846581351},{"elapsed_time":713685,"interval":1,"segment":1,"source_type":4,"start_time":1705846582351},{"elapsed_time":714685,"interval":1,"segment":1,"source_type":4,"start_time":1705846583351},{"elapsed_time":715685,"interval":1,"segment":1,"source_type":4,"start_time":1705846584351},{"elapsed_time":716685,"interval":1,"segment":1,"source_type":4,"start_time":1705846585351},{"elapsed_time":717685,"interval":1,"segment":1,"source_type":4,"start_time":1705846586351},{"elapsed_time":718685,"interval":1,"segment":1,"source_type":4,"start_time":1705846587351},{"elapsed_time":719685,"interval":1,"segment":1,"source_type":4,"start_time":1705846588351},{"elapsed_time":720685,"interval":1,"segment":1,"source_type":4,"start_time":1705846589351},{"elapsed_time":721685,"interval":1,"segment":1,"source_type":4,"start_time":1705846590351},{"elapsed_time":722685,"interval":1,"segment":1,"source_type":4,"start_time":1705846591351},{"elapsed_time":723685,"interval":1,"segment":1,"source_type":4,"start_time":1705846592351},{"elapsed_time":724685,"interval":1,"segment":1,"source_type":4,"start_time":1705846593351},{"elapsed_time":725685,"interval":1,"segment":1,"source_type":4,"start_time":1705846594351},{"elapsed_time":726685,"interval":1,"segment":1,"source_type":4,"start_time":1705846595351},{"elapsed_time":727685,"interval":1,"segment":1,"source_type":4,"start_time":1705846596351},{"elapsed_time":728685,"interval":1,"segment":1,"source_type":4,"start_time":1705846597351},{"elapsed_time":729685,"interval":1,"segment":1,"source_type":4,"start_time":1705846598351},{"elapsed_time":730685,"interval":1,"segment":1,"source_type":4,"start_time":1705846599351},{"elapsed_time":731685,"interval":1,"segment":1,"source_type":4,"start_time":1705846600351},{"elapsed_time":732685,"interval":1,"segment":1,"source_type":4,"start_time":1705846601351},{"elapsed_time":733685,"interval":1,"segment":1,"source_type":4,"start_time":1705846602351},{"elapsed_time":734685,"interval":1,"segment":1,"source_type":4,"start_time":1705846603351},{"elapsed_time":735685,"interval":1,"segment":1,"source_type":4,"start_time":1705846604351},{"elapsed_time":736685,"interval":1,"segment":1,"source_type":4,"start_time":1705846605351},{"elapsed_time":737685,"interval":1,"segment":1,"source_type":4,"start_time":1705846606351},{"elapsed_time":738685,"interval":1,"segment":1,"source_type":4,"start_time":1705846607351},{"elapsed_time":739685,"interval":1,"segment":1,"source_type":4,"start_time":1705846608351},{"elapsed_time":740685,"interval":1,"segment":1,"source_type":4,"start_time":1705846609351},{"elapsed_time":741685,"interval":1,"segment":1,"source_type":4,"start_time":1705846610351},{"elapsed_time":742685,"interval":1,"segment":1,"source_type":4,"start_time":1705846611351},{"elapsed_time":743685,"interval":1,"segment":1,"source_type":4,"start_time":1705846612351},{"elapsed_time":744685,"interval":1,"segment":1,"source_type":4,"start_time":1705846613351},{"elapsed_time":745685,"interval":1,"segment":1,"source_type":4,"start_time":1705846614351},{"elapsed_time":746685,"interval":1,"segment":1,"source_type":4,"start_time":1705846615351},{"elapsed_time":747685,"interval":1,"segment":1,"source_type":4,"start_time":1705846616351},{"elapsed_time":748685,"interval":1,"segment":1,"source_type":4,"start_time":1705846617351},{"elapsed_time":749685,"interval":1,"segment":1,"source_type":4,"start_time":1705846618351},{"elapsed_time":750755,"interval":1,"segment":1,"source_type":4,"start_time":1705846619421},{"elapsed_time":751755,"interval":1,"segment":1,"source_type":4,"start_time":1705846620421},{"elapsed_time":752755,"interval":1,"segment":1,"source_type":4,"start_time":1705846621421},{"elapsed_time":753755,"interval":1,"segment":1,"source_type":4,"start_time":1705846622421},{"elapsed_time":754755,"interval":1,"segment":1,"source_type":4,"start_time":1705846623421},{"elapsed_time":755755,"interval":1,"segment":1,"source_type":4,"start_time":1705846624421},{"elapsed_time":756755,"interval":1,"segment":1,"source_type":4,"start_time":1705846625421},{"elapsed_time":757755,"interval":1,"segment":1,"source_type":4,"start_time":1705846626421},{"elapsed_time":758755,"interval":1,"segment":1,"source_type":4,"start_time":1705846627421},{"elapsed_time":759755,"interval":1,"segment":1,"source_type":4,"start_time":1705846628421},{"elapsed_time":760755,"interval":1,"segment":1,"source_type":4,"start_time":1705846629421},{"elapsed_time":761755,"interval":1,"segment":1,"source_type":4,"start_time":1705846630421},{"elapsed_time":762755,"interval":1,"segment":1,"source_type":4,"start_time":1705846631421},{"elapsed_time":763755,"interval":1,"segment":1,"source_type":4,"start_time":1705846632421},{"elapsed_time":764755,"interval":1,"segment":1,"source_type":4,"start_time":1705846633421},{"elapsed_time":765755,"interval":1,"segment":1,"source_type":4,"start_time":1705846634421},{"elapsed_time":766755,"interval":1,"segment":1,"source_type":4,"start_time":1705846635421},{"elapsed_time":767755,"interval":1,"segment":1,"source_type":4,"start_time":1705846636421},{"elapsed_time":768755,"interval":1,"segment":1,"source_type":4,"start_time":1705846637421},{"elapsed_time":769755,"interval":1,"segment":1,"source_type":4,"start_time":1705846638421},{"elapsed_time":770755,"interval":1,"segment":1,"source_type":4,"start_time":1705846639421},{"elapsed_time":771755,"interval":1,"segment":1,"source_type":4,"start_time":1705846640421},{"elapsed_time":772755,"interval":1,"segment":1,"source_type":4,"start_time":1705846641421},{"elapsed_time":773755,"interval":1,"segment":1,"source_type":4,"start_time":1705846642421},{"elapsed_time":774755,"interval":1,"segment":1,"source_type":4,"start_time":1705846643421},{"elapsed_time":775755,"interval":1,"segment":1,"source_type":4,"start_time":1705846644421},{"elapsed_time":776755,"interval":1,"segment":1,"source_type":4,"start_time":1705846645421},{"elapsed_time":777755,"interval":1,"segment":1,"source_type":4,"start_time":1705846646421},{"elapsed_time":778755,"interval":1,"segment":1,"source_type":4,"start_time":1705846647421},{"elapsed_time":779755,"interval":1,"segment":1,"source_type":4,"start_time":1705846648421},{"elapsed_time":780755,"interval":1,"segment":1,"source_type":4,"start_time":1705846649421},{"elapsed_time":781755,"interval":1,"segment":1,"source_type":4,"start_time":1705846650421},{"elapsed_time":782755,"interval":1,"segment":1,"source_type":4,"start_time":1705846651421},{"elapsed_time":783755,"interval":1,"segment":1,"source_type":4,"start_time":1705846652421},{"elapsed_time":784755,"interval":1,"segment":1,"source_type":4,"start_time":1705846653421},{"elapsed_time":785755,"interval":1,"segment":1,"source_type":4,"start_time":1705846654421},{"elapsed_time":786755,"interval":1,"segment":1,"source_type":4,"start_time":1705846655421},{"elapsed_time":787755,"interval":1,"segment":1,"source_type":4,"start_time":1705846656421},{"elapsed_time":788755,"interval":1,"segment":1,"source_type":4,"start_time":1705846657421},{"elapsed_time":789721,"interval":1,"segment":1,"source_type":4,"start_time":1705846658387},{"elapsed_time":790721,"interval":1,"segment":1,"source_type":4,"start_time":1705846659387},{"elapsed_time":791721,"interval":1,"segment":1,"source_type":4,"start_time":1705846660387},{"elapsed_time":792722,"interval":1,"segment":1,"source_type":4,"start_time":1705846661388},{"elapsed_time":793722,"interval":1,"segment":1,"source_type":4,"start_time":1705846662388},{"elapsed_time":794722,"interval":1,"segment":1,"source_type":4,"start_time":1705846663388},{"elapsed_time":795722,"interval":1,"segment":1,"source_type":4,"start_time":1705846664388},{"elapsed_time":796722,"interval":1,"segment":1,"source_type":4,"start_time":1705846665388},{"elapsed_time":797722,"interval":1,"segment":1,"source_type":4,"start_time":1705846666388},{"elapsed_time":798722,"interval":1,"segment":1,"source_type":4,"start_time":1705846667388},{"elapsed_time":799722,"interval":1,"segment":1,"source_type":4,"start_time":1705846668388},{"elapsed_time":800722,"interval":1,"segment":1,"source_type":4,"start_time":1705846669388},{"elapsed_time":801722,"interval":1,"segment":1,"source_type":4,"start_time":1705846670388},{"elapsed_time":802722,"interval":1,"segment":1,"source_type":4,"start_time":1705846671388},{"elapsed_time":803698,"interval":1,"segment":1,"source_type":4,"start_time":1705846672364},{"elapsed_time":805245,"interval":1,"segment":1,"source_type":4,"start_time":1705846673911},{"elapsed_time":806245,"interval":1,"segment":1,"source_type":4,"start_time":1705846674911},{"elapsed_time":807245,"interval":1,"segment":1,"source_type":4,"start_time":1705846675911},{"elapsed_time":808245,"interval":1,"segment":1,"source_type":4,"start_time":1705846676911},{"elapsed_time":809245,"interval":1,"segment":1,"source_type":4,"start_time":1705846677911},{"elapsed_time":810245,"interval":1,"segment":1,"source_type":4,"start_time":1705846678911},{"elapsed_time":811245,"interval":1,"segment":1,"source_type":4,"start_time":1705846679911},{"elapsed_time":812245,"interval":1,"segment":1,"source_type":4,"start_time":1705846680911},{"elapsed_time":813245,"interval":1,"segment":1,"source_type":4,"start_time":1705846681911},{"elapsed_time":814245,"interval":1,"segment":1,"source_type":4,"start_time":1705846682911},{"elapsed_time":815245,"interval":1,"segment":1,"source_type":4,"start_time":1705846683911},{"elapsed_time":816245,"interval":1,"segment":1,"source_type":4,"start_time":1705846684911},{"elapsed_time":817245,"interval":1,"segment":1,"source_type":4,"start_time":1705846685911},{"elapsed_time":818245,"interval":1,"segment":1,"source_type":4,"start_time":1705846686911},{"elapsed_time":819245,"interval":1,"segment":1,"source_type":4,"start_time":1705846687911},{"elapsed_time":820245,"interval":1,"segment":1,"source_type":4,"start_time":1705846688911},{"elapsed_time":821328,"interval":1,"segment":1,"source_type":4,"start_time":1705846689994},{"elapsed_time":822670,"interval":1,"segment":1,"source_type":4,"start_time":1705846691336},{"elapsed_time":823670,"interval":1,"segment":1,"source_type":4,"start_time":1705846692336},{"elapsed_time":824670,"interval":1,"segment":1,"source_type":4,"start_time":1705846693336},{"elapsed_time":825670,"interval":1,"segment":1,"source_type":4,"start_time":1705846694336},{"elapsed_time":826670,"interval":1,"segment":1,"source_type":4,"start_time":1705846695336},{"elapsed_time":827670,"interval":1,"segment":1,"source_type":4,"start_time":1705846696336},{"elapsed_time":828670,"interval":1,"segment":1,"source_type":4,"start_time":1705846697336},{"elapsed_time":829670,"interval":1,"segment":1,"source_type":4,"start_time":1705846698336},{"elapsed_time":830670,"interval":1,"segment":1,"source_type":4,"start_time":1705846699336},{"elapsed_time":831670,"interval":1,"segment":1,"source_type":4,"start_time":1705846700336},{"elapsed_time":832670,"interval":1,"segment":1,"source_type":4,"start_time":1705846701336},{"elapsed_time":833670,"interval":1,"segment":1,"source_type":4,"start_time":1705846702336},{"elapsed_time":834670,"interval":1,"segment":1,"source_type":4,"start_time":1705846703336},{"elapsed_time":835670,"interval":1,"segment":1,"source_type":4,"start_time":1705846704336},{"elapsed_time":836670,"interval":1,"segment":1,"source_type":4,"start_time":1705846705336},{"elapsed_time":837670,"interval":1,"segment":1,"source_type":4,"start_time":1705846706336},{"elapsed_time":838670,"interval":1,"segment":1,"source_type":4,"start_time":1705846707336},{"elapsed_time":839670,"interval":1,"segment":1,"source_type":4,"start_time":1705846708336},{"elapsed_time":840670,"interval":1,"segment":1,"source_type":4,"start_time":1705846709336},{"elapsed_time":841670,"interval":1,"segment":1,"source_type":4,"start_time":1705846710336},{"elapsed_time":842670,"interval":1,"segment":1,"source_type":4,"start_time":1705846711336},{"elapsed_time":843670,"interval":1,"segment":1,"source_type":4,"start_time":1705846712336},{"elapsed_time":844670,"interval":1,"segment":1,"source_type":4,"start_time":1705846713336},{"elapsed_time":845670,"interval":1,"segment":1,"source_type":4,"start_time":1705846714336},{"elapsed_time":846670,"interval":1,"segment":1,"source_type":4,"start_time":1705846715336},{"elapsed_time":847670,"interval":1,"segment":1,"source_type":4,"start_time":1705846716336},{"elapsed_time":848670,"interval":1,"segment":1,"source_type":4,"start_time":1705846717336},{"elapsed_time":849670,"interval":1,"segment":1,"source_type":4,"start_time":1705846718336},{"elapsed_time":850670,"interval":1,"segment":1,"source_type":4,"start_time":1705846719336},{"elapsed_time":851670,"interval":1,"segment":1,"source_type":4,"start_time":1705846720336},{"elapsed_time":852670,"interval":1,"segment":1,"source_type":4,"start_time":1705846721336},{"elapsed_time":853670,"interval":1,"segment":1,"source_type":4,"start_time":1705846722336},{"elapsed_time":854670,"interval":1,"segment":1,"source_type":4,"start_time":1705846723336},{"elapsed_time":855670,"interval":1,"segment":1,"source_type":4,"start_time":1705846724336},{"elapsed_time":857729,"interval":1,"segment":1,"source_type":4,"start_time":1705846726395},{"elapsed_time":858729,"interval":1,"segment":1,"source_type":4,"start_time":1705846727395},{"elapsed_time":859729,"interval":1,"segment":1,"source_type":4,"start_time":1705846728395},{"elapsed_time":860729,"interval":1,"segment":1,"source_type":4,"start_time":1705846729395},{"elapsed_time":861729,"interval":1,"segment":1,"source_type":4,"start_time":1705846730395},{"elapsed_time":862729,"interval":1,"segment":1,"source_type":4,"start_time":1705846731395},{"elapsed_time":863729,"interval":1,"segment":1,"source_type":4,"start_time":1705846732395},{"elapsed_time":864729,"interval":1,"segment":1,"source_type":4,"start_time":1705846733395},{"elapsed_time":865729,"interval":1,"segment":1,"source_type":4,"start_time":1705846734395},{"elapsed_time":866729,"interval":1,"segment":1,"source_type":4,"start_time":1705846735395},{"elapsed_time":867729,"interval":1,"segment":1,"source_type":4,"start_time":1705846736395},{"elapsed_time":868729,"interval":1,"segment":1,"source_type":4,"start_time":1705846737395},{"elapsed_time":869633,"interval":1,"segment":1,"source_type":4,"start_time":1705846738299},{"elapsed_time":869729,"interval":1,"segment":1,"source_type":4,"start_time":1705846738395},{"elapsed_time":870121,"interval":1,"segment":1,"source_type":4,"start_time":1705846738787},{"elapsed_time":870729,"interval":1,"segment":1,"source_type":4,"start_time":1705846739395},{"elapsed_time":871121,"interval":1,"segment":1,"source_type":4,"start_time":1705846739787},{"elapsed_time":872121,"interval":1,"segment":1,"source_type":4,"start_time":1705846740787},{"elapsed_time":873121,"interval":1,"segment":1,"source_type":4,"start_time":1705846741787},{"elapsed_time":874121,"interval":1,"segment":1,"source_type":4,"start_time":1705846742787},{"elapsed_time":875121,"interval":1,"segment":1,"source_type":4,"start_time":1705846743787},{"elapsed_time":876121,"interval":1,"segment":1,"source_type":4,"start_time":1705846744787},{"elapsed_time":877121,"interval":1,"segment":1,"source_type":4,"start_time":1705846745787},{"elapsed_time":878121,"interval":1,"segment":1,"source_type":4,"start_time":1705846746787},{"elapsed_time":879121,"interval":1,"segment":1,"source_type":4,"start_time":1705846747787},{"elapsed_time":880121,"interval":1,"segment":1,"source_type":4,"start_time":1705846748787},{"elapsed_time":881121,"interval":1,"segment":1,"source_type":4,"start_time":1705846749787},{"elapsed_time":882121,"interval":1,"segment":1,"source_type":4,"start_time":1705846750787},{"elapsed_time":883121,"interval":1,"segment":1,"source_type":4,"start_time":1705846751787},{"elapsed_time":884121,"interval":1,"segment":1,"source_type":4,"start_time":1705846752787},{"elapsed_time":885121,"interval":1,"segment":1,"source_type":4,"start_time":1705846753787},{"elapsed_time":886121,"interval":1,"segment":1,"source_type":4,"start_time":1705846754787},{"elapsed_time":887121,"interval":1,"segment":1,"source_type":4,"start_time":1705846755787},{"elapsed_time":888121,"interval":1,"segment":1,"source_type":4,"start_time":1705846756787},{"elapsed_time":889121,"interval":1,"segment":1,"source_type":4,"start_time":1705846757787},{"elapsed_time":890121,"interval":1,"segment":1,"source_type":4,"start_time":1705846758787},{"elapsed_time":891122,"interval":1,"segment":1,"source_type":4,"start_time":1705846759788},{"elapsed_time":892122,"interval":1,"segment":1,"source_type":4,"start_time":1705846760788},{"elapsed_time":893122,"interval":1,"segment":1,"source_type":4,"start_time":1705846761788},{"elapsed_time":894122,"interval":1,"segment":1,"source_type":4,"start_time":1705846762788},{"elapsed_time":896169,"interval":1,"segment":1,"source_type":4,"start_time":1705846764835},{"elapsed_time":897169,"interval":1,"segment":1,"source_type":4,"start_time":1705846765835},{"elapsed_time":898169,"interval":1,"segment":1,"source_type":4,"start_time":1705846766835},{"elapsed_time":899172,"interval":1,"segment":1,"source_type":4,"start_time":1705846767838},{"elapsed_time":901574,"interval":1,"segment":1,"source_type":4,"start_time":1705846770240},{"elapsed_time":902574,"interval":1,"segment":1,"source_type":4,"start_time":1705846771240},{"elapsed_time":903574,"interval":1,"segment":1,"source_type":4,"start_time":1705846772240},{"elapsed_time":904574,"interval":1,"segment":1,"source_type":4,"start_time":1705846773240},{"elapsed_time":905574,"interval":1,"segment":1,"source_type":4,"start_time":1705846774240},{"elapsed_time":906574,"interval":1,"segment":1,"source_type":4,"start_time":1705846775240},{"elapsed_time":907574,"interval":1,"segment":1,"source_type":4,"start_time":1705846776240},{"elapsed_time":908574,"interval":1,"segment":1,"source_type":4,"start_time":1705846777240},{"elapsed_time":909574,"interval":1,"segment":1,"source_type":4,"start_time":1705846778240},{"elapsed_time":910574,"interval":1,"segment":1,"source_type":4,"start_time":1705846779240},{"elapsed_time":911574,"interval":1,"segment":1,"source_type":4,"start_time":1705846780240},{"elapsed_time":912574,"interval":1,"segment":1,"source_type":4,"start_time":1705846781240},{"elapsed_time":913574,"interval":1,"segment":1,"source_type":4,"start_time":1705846782240},{"elapsed_time":914574,"interval":1,"segment":1,"source_type":4,"start_time":1705846783240},{"elapsed_time":915574,"interval":1,"segment":1,"source_type":4,"start_time":1705846784240},{"elapsed_time":916574,"interval":1,"segment":1,"source_type":4,"start_time":1705846785240},{"elapsed_time":917574,"interval":1,"segment":1,"source_type":4,"start_time":1705846786240},{"elapsed_time":918574,"interval":1,"segment":1,"source_type":4,"start_time":1705846787240},{"elapsed_time":919574,"interval":1,"segment":1,"source_type":4,"start_time":1705846788240},{"elapsed_time":920574,"interval":1,"segment":1,"source_type":4,"start_time":1705846789240},{"elapsed_time":921574,"interval":1,"segment":1,"source_type":4,"start_time":1705846790240},{"elapsed_time":922574,"interval":1,"segment":1,"source_type":4,"start_time":1705846791240},{"elapsed_time":923574,"interval":1,"segment":1,"source_type":4,"start_time":1705846792240},{"elapsed_time":924574,"interval":1,"segment":1,"source_type":4,"start_time":1705846793240},{"elapsed_time":924677,"interval":1,"segment":1,"source_type":4,"start_time":1705846793343},{"elapsed_time":925585,"interval":1,"segment":1,"source_type":4,"start_time":1705846794251},{"elapsed_time":926585,"interval":1,"segment":1,"source_type":4,"start_time":1705846795251},{"elapsed_time":927585,"interval":1,"segment":1,"source_type":4,"start_time":1705846796251},{"elapsed_time":928585,"interval":1,"segment":1,"source_type":4,"start_time":1705846797251},{"elapsed_time":929585,"interval":1,"segment":1,"source_type":4,"start_time":1705846798251},{"elapsed_time":930585,"interval":1,"segment":1,"source_type":4,"start_time":1705846799251},{"elapsed_time":931585,"interval":1,"segment":1,"source_type":4,"start_time":1705846800251},{"elapsed_time":932585,"interval":1,"segment":1,"source_type":4,"start_time":1705846801251},{"elapsed_time":933585,"interval":1,"segment":1,"source_type":4,"start_time":1705846802251},{"elapsed_time":934585,"interval":1,"segment":1,"source_type":4,"start_time":1705846803251},{"elapsed_time":935585,"interval":1,"segment":1,"source_type":4,"start_time":1705846804251},{"elapsed_time":936585,"interval":1,"segment":1,"source_type":4,"start_time":1705846805251},{"elapsed_time":937585,"interval":1,"segment":1,"source_type":4,"start_time":1705846806251},{"elapsed_time":938585,"interval":1,"segment":1,"source_type":4,"start_time":1705846807251},{"elapsed_time":939585,"interval":1,"segment":1,"source_type":4,"start_time":1705846808251},{"elapsed_time":940585,"interval":1,"segment":1,"source_type":4,"start_time":1705846809251},{"elapsed_time":941585,"interval":1,"segment":1,"source_type":4,"start_time":1705846810251},{"elapsed_time":942585,"interval":1,"segment":1,"source_type":4,"start_time":1705846811251},{"elapsed_time":943585,"interval":1,"segment":1,"source_type":4,"start_time":1705846812251},{"elapsed_time":944585,"interval":1,"segment":1,"source_type":4,"start_time":1705846813251},{"elapsed_time":945585,"interval":1,"segment":1,"source_type":4,"start_time":1705846814251},{"elapsed_time":946585,"interval":1,"segment":1,"source_type":4,"start_time":1705846815251},{"elapsed_time":947585,"interval":1,"segment":1,"source_type":4,"start_time":1705846816251},{"elapsed_time":948585,"interval":1,"segment":1,"source_type":4,"start_time":1705846817251},{"elapsed_time":949585,"interval":1,"segment":1,"source_type":4,"start_time":1705846818251},{"elapsed_time":950585,"interval":1,"segment":1,"source_type":4,"start_time":1705846819251},{"elapsed_time":951585,"interval":1,"segment":1,"source_type":4,"start_time":1705846820251},{"elapsed_time":952585,"interval":1,"segment":1,"source_type":4,"start_time":1705846821251},{"elapsed_time":953585,"interval":1,"segment":1,"source_type":4,"start_time":1705846822251},{"elapsed_time":954585,"interval":1,"segment":1,"source_type":4,"start_time":1705846823251},{"elapsed_time":955585,"interval":1,"segment":1,"source_type":4,"start_time":1705846824251},{"elapsed_time":956585,"interval":1,"segment":1,"source_type":4,"start_time":1705846825251},{"elapsed_time":957585,"interval":1,"segment":1,"source_type":4,"start_time":1705846826251},{"elapsed_time":958585,"interval":1,"segment":1,"source_type":4,"start_time":1705846827251},{"elapsed_time":959585,"interval":1,"segment":1,"source_type":4,"start_time":1705846828251},{"elapsed_time":960585,"interval":1,"segment":1,"source_type":4,"start_time":1705846829251},{"elapsed_time":961585,"interval":1,"segment":1,"source_type":4,"start_time":1705846830251},{"elapsed_time":962585,"interval":1,"segment":1,"source_type":4,"start_time":1705846831251},{"elapsed_time":963585,"interval":1,"segment":1,"source_type":4,"start_time":1705846832251},{"elapsed_time":964585,"interval":1,"segment":1,"source_type":4,"start_time":1705846833251},{"elapsed_time":965585,"interval":1,"segment":1,"source_type":4,"start_time":1705846834251},{"elapsed_time":966585,"interval":1,"segment":1,"source_type":4,"start_time":1705846835251},{"elapsed_time":967585,"interval":1,"segment":1,"source_type":4,"start_time":1705846836251},{"elapsed_time":968585,"interval":1,"segment":1,"source_type":4,"start_time":1705846837251},{"elapsed_time":969585,"interval":1,"segment":1,"source_type":4,"start_time":1705846838251},{"elapsed_time":970585,"interval":1,"segment":1,"source_type":4,"start_time":1705846839251},{"elapsed_time":971585,"interval":1,"segment":1,"source_type":4,"start_time":1705846840251},{"elapsed_time":972585,"interval":1,"segment":1,"source_type":4,"start_time":1705846841251},{"elapsed_time":973585,"interval":1,"segment":1,"source_type":4,"start_time":1705846842251},{"elapsed_time":974585,"interval":1,"segment":1,"source_type":4,"start_time":1705846843251},{"elapsed_time":975585,"interval":1,"segment":1,"source_type":4,"start_time":1705846844251},{"elapsed_time":976585,"interval":1,"segment":1,"source_type":4,"start_time":1705846845251},{"elapsed_time":977585,"interval":1,"segment":1,"source_type":4,"start_time":1705846846251},{"elapsed_time":978585,"interval":1,"segment":1,"source_type":4,"start_time":1705846847251},{"elapsed_time":979585,"interval":1,"segment":1,"source_type":4,"start_time":1705846848251},{"elapsed_time":980585,"interval":1,"segment":1,"source_type":4,"start_time":1705846849251},{"elapsed_time":981585,"interval":1,"segment":1,"source_type":4,"start_time":1705846850251},{"elapsed_time":982585,"interval":1,"segment":1,"source_type":4,"start_time":1705846851251},{"elapsed_time":983585,"interval":1,"segment":1,"source_type":4,"start_time":1705846852251},{"elapsed_time":984585,"interval":1,"segment":1,"source_type":4,"start_time":1705846853251},{"elapsed_time":985585,"interval":1,"segment":1,"source_type":4,"start_time":1705846854251},{"elapsed_time":986585,"interval":1,"segment":1,"source_type":4,"start_time":1705846855251},{"elapsed_time":987585,"interval":1,"segment":1,"source_type":4,"start_time":1705846856251},{"elapsed_time":988585,"interval":1,"segment":1,"source_type":4,"start_time":1705846857251},{"elapsed_time":989585,"interval":1,"segment":1,"source_type":4,"start_time":1705846858251},{"elapsed_time":990585,"interval":1,"segment":1,"source_type":4,"start_time":1705846859251},{"elapsed_time":991585,"interval":1,"segment":1,"source_type":4,"start_time":1705846860251},{"elapsed_time":992585,"interval":1,"segment":1,"source_type":4,"start_time":1705846861251},{"elapsed_time":993585,"interval":1,"segment":1,"source_type":4,"start_time":1705846862251},{"elapsed_time":994585,"interval":1,"segment":1,"source_type":4,"start_time":1705846863251},{"elapsed_time":995585,"interval":1,"segment":1,"source_type":4,"start_time":1705846864251},{"elapsed_time":996585,"interval":1,"segment":1,"source_type":4,"start_time":1705846865251},{"elapsed_time":997585,"interval":1,"segment":1,"source_type":4,"start_time":1705846866251},{"elapsed_time":998585,"interval":1,"segment":1,"source_type":4,"start_time":1705846867251},{"elapsed_time":999585,"interval":1,"segment":1,"source_type":4,"start_time":1705846868251},{"elapsed_time":1000585,"interval":1,"segment":1,"source_type":4,"start_time":1705846869251},{"elapsed_time":1001585,"interval":1,"segment":1,"source_type":4,"start_time":1705846870251},{"elapsed_time":1002585,"interval":1,"segment":1,"source_type":4,"start_time":1705846871251},{"elapsed_time":1003585,"interval":1,"segment":1,"source_type":4,"start_time":1705846872251},{"elapsed_time":1004585,"interval":1,"segment":1,"source_type":4,"start_time":1705846873251},{"elapsed_time":1005585,"interval":1,"segment":1,"source_type":4,"start_time":1705846874251},{"elapsed_time":1006593,"interval":1,"segment":1,"source_type":4,"start_time":1705846875259},{"elapsed_time":1008020,"interval":1,"segment":1,"source_type":4,"start_time":1705846876686},{"elapsed_time":1009020,"interval":1,"segment":1,"source_type":4,"start_time":1705846877686},{"elapsed_time":1010020,"interval":1,"segment":1,"source_type":4,"start_time":1705846878686},{"elapsed_time":1011020,"interval":1,"segment":1,"source_type":4,"start_time":1705846879686},{"elapsed_time":1012020,"interval":1,"segment":1,"source_type":4,"start_time":1705846880686},{"elapsed_time":1013020,"interval":1,"segment":1,"source_type":4,"start_time":1705846881686},{"elapsed_time":1014020,"interval":1,"segment":1,"source_type":4,"start_time":1705846882686},{"elapsed_time":1015019,"interval":1,"segment":1,"source_type":4,"start_time":1705846883685},{"elapsed_time":1016019,"interval":1,"segment":1,"source_type":4,"start_time":1705846884685},{"elapsed_time":1017019,"interval":1,"segment":1,"source_type":4,"start_time":1705846885685},{"elapsed_time":1018248,"interval":1,"segment":1,"source_type":4,"start_time":1705846886914},{"elapsed_time":1019248,"interval":1,"segment":1,"source_type":4,"start_time":1705846887914},{"elapsed_time":1020248,"interval":1,"segment":1,"source_type":4,"start_time":1705846888914},{"elapsed_time":1021248,"interval":1,"segment":1,"source_type":4,"start_time":1705846889914},{"elapsed_time":1022248,"interval":1,"segment":1,"source_type":4,"start_time":1705846890914},{"elapsed_time":1023248,"interval":1,"segment":1,"source_type":4,"start_time":1705846891914},{"elapsed_time":1024248,"interval":1,"segment":1,"source_type":4,"start_time":1705846892914},{"elapsed_time":1025248,"interval":1,"segment":1,"source_type":4,"start_time":1705846893914},{"elapsed_time":1026248,"interval":1,"segment":1,"source_type":4,"start_time":1705846894914},{"elapsed_time":1027248,"interval":1,"segment":1,"source_type":4,"start_time":1705846895914},{"elapsed_time":1028248,"interval":1,"segment":1,"source_type":4,"start_time":1705846896914},{"elapsed_time":1030256,"interval":1,"segment":1,"source_type":4,"start_time":1705846898922},{"elapsed_time":1031234,"interval":1,"segment":1,"source_type":4,"start_time":1705846899900},{"elapsed_time":1032234,"interval":1,"segment":1,"source_type":4,"start_time":1705846900900},{"elapsed_time":1033234,"interval":1,"segment":1,"source_type":4,"start_time":1705846901900},{"elapsed_time":1034234,"interval":1,"segment":1,"source_type":4,"start_time":1705846902900},{"elapsed_time":1035234,"interval":1,"segment":1,"source_type":4,"start_time":1705846903900},{"elapsed_time":1036234,"interval":1,"segment":1,"source_type":4,"start_time":1705846904900},{"elapsed_time":1037234,"interval":1,"segment":1,"source_type":4,"start_time":1705846905900},{"elapsed_time":1038234,"interval":1,"segment":1,"source_type":4,"start_time":1705846906900},{"elapsed_time":1039234,"interval":1,"segment":1,"source_type":4,"start_time":1705846907900},{"elapsed_time":1040234,"interval":1,"segment":1,"source_type":4,"start_time":1705846908900},{"elapsed_time":1041234,"interval":1,"segment":1,"source_type":4,"start_time":1705846909900},{"elapsed_time":1042234,"interval":1,"segment":1,"source_type":4,"start_time":1705846910900},{"elapsed_time":1043234,"interval":1,"segment":1,"source_type":4,"start_time":1705846911900},{"elapsed_time":1043984,"interval":1,"segment":1,"source_type":4,"start_time":1705846912650},{"elapsed_time":1044984,"interval":1,"segment":1,"source_type":4,"start_time":1705846913650},{"elapsed_time":1045984,"interval":1,"segment":1,"source_type":4,"start_time":1705846914650},{"elapsed_time":1046984,"interval":1,"segment":1,"source_type":4,"start_time":1705846915650},{"elapsed_time":1047984,"interval":1,"segment":1,"source_type":4,"start_time":1705846916650},{"elapsed_time":1048984,"interval":1,"segment":1,"source_type":4,"start_time":1705846917650},{"elapsed_time":1049984,"interval":1,"segment":1,"source_type":4,"start_time":1705846918650},{"elapsed_time":1050984,"interval":1,"segment":1,"source_type":4,"start_time":1705846919650},{"elapsed_time":1051984,"interval":1,"segment":1,"source_type":4,"start_time":1705846920650},{"elapsed_time":1052984,"interval":1,"segment":1,"source_type":4,"start_time":1705846921650},{"elapsed_time":1053984,"interval":1,"segment":1,"source_type":4,"start_time":1705846922650},{"elapsed_time":1054984,"interval":1,"segment":1,"source_type":4,"start_time":1705846923650},{"elapsed_time":1055984,"interval":1,"segment":1,"source_type":4,"start_time":1705846924650},{"elapsed_time":1056984,"interval":1,"segment":1,"source_type":4,"start_time":1705846925650},{"elapsed_time":1057984,"interval":1,"segment":1,"source_type":4,"start_time":1705846926650},{"elapsed_time":1058984,"interval":1,"segment":1,"source_type":4,"start_time":1705846927650},{"elapsed_time":1059984,"interval":1,"segment":1,"source_type":4,"start_time":1705846928650},{"elapsed_time":1060984,"interval":1,"segment":1,"source_type":4,"start_time":1705846929650},{"elapsed_time":1061984,"interval":1,"segment":1,"source_type":4,"start_time":1705846930650},{"elapsed_time":1062984,"interval":1,"segment":1,"source_type":4,"start_time":1705846931650},{"elapsed_time":1063984,"interval":1,"segment":1,"source_type":4,"start_time":1705846932650},{"elapsed_time":1064984,"interval":1,"segment":1,"source_type":4,"start_time":1705846933650},{"elapsed_time":1065984,"interval":1,"segment":1,"source_type":4,"start_time":1705846934650},{"elapsed_time":1066984,"interval":1,"segment":1,"source_type":4,"start_time":1705846935650},{"elapsed_time":1067984,"interval":1,"segment":1,"source_type":4,"start_time":1705846936650},{"elapsed_time":1068984,"interval":1,"segment":1,"source_type":4,"start_time":1705846937650},{"elapsed_time":1069984,"interval":1,"segment":1,"source_type":4,"start_time":1705846938650},{"elapsed_time":1070984,"interval":1,"segment":1,"source_type":4,"start_time":1705846939650},{"elapsed_time":1071984,"interval":1,"segment":1,"source_type":4,"start_time":1705846940650},{"elapsed_time":1072984,"interval":1,"segment":1,"source_type":4,"start_time":1705846941650},{"elapsed_time":1073984,"interval":1,"segment":1,"source_type":4,"start_time":1705846942650},{"elapsed_time":1074984,"interval":1,"segment":1,"source_type":4,"start_time":1705846943650},{"elapsed_time":1075984,"interval":1,"segment":1,"source_type":4,"start_time":1705846944650},{"elapsed_time":1076984,"interval":1,"segment":1,"source_type":4,"start_time":1705846945650},{"elapsed_time":1077984,"interval":1,"segment":1,"source_type":4,"start_time":1705846946650},{"elapsed_time":1078984,"interval":1,"segment":1,"source_type":4,"start_time":1705846947650},{"elapsed_time":1079984,"interval":1,"segment":1,"source_type":4,"start_time":1705846948650},{"elapsed_time":1080984,"interval":1,"segment":1,"source_type":4,"start_time":1705846949650},{"elapsed_time":1081984,"interval":1,"segment":1,"source_type":4,"start_time":1705846950650},{"elapsed_time":1082984,"interval":1,"segment":1,"source_type":4,"start_time":1705846951650},{"elapsed_time":1083984,"interval":1,"segment":1,"source_type":4,"start_time":1705846952650},{"elapsed_time":1084984,"interval":1,"segment":1,"source_type":4,"start_time":1705846953650},{"elapsed_time":1085984,"interval":1,"segment":1,"source_type":4,"start_time":1705846954650},{"elapsed_time":1086984,"interval":1,"segment":1,"source_type":4,"start_time":1705846955650},{"elapsed_time":1087984,"interval":1,"segment":1,"source_type":4,"start_time":1705846956650},{"elapsed_time":1088984,"interval":1,"segment":1,"source_type":4,"start_time":1705846957650},{"elapsed_time":1089984,"interval":1,"segment":1,"source_type":4,"start_time":1705846958650},{"elapsed_time":1090984,"interval":1,"segment":1,"source_type":4,"start_time":1705846959650},{"elapsed_time":1091984,"interval":1,"segment":1,"source_type":4,"start_time":1705846960650},{"elapsed_time":1092984,"interval":1,"segment":1,"source_type":4,"start_time":1705846961650},{"elapsed_time":1093984,"interval":1,"segment":1,"source_type":4,"start_time":1705846962650},{"elapsed_time":1094984,"interval":1,"segment":1,"source_type":4,"start_time":1705846963650},{"elapsed_time":1095984,"interval":1,"segment":1,"source_type":4,"start_time":1705846964650},{"elapsed_time":1096984,"interval":1,"segment":1,"source_type":4,"start_time":1705846965650},{"elapsed_time":1097984,"interval":1,"segment":1,"source_type":4,"start_time":1705846966650},{"elapsed_time":1098984,"interval":1,"segment":1,"source_type":4,"start_time":1705846967650},{"elapsed_time":1099984,"interval":1,"segment":1,"source_type":4,"start_time":1705846968650},{"elapsed_time":1100984,"interval":1,"segment":1,"source_type":4,"start_time":1705846969650},{"elapsed_time":1101984,"interval":1,"segment":1,"source_type":4,"start_time":1705846970650},{"elapsed_time":1102984,"interval":1,"segment":1,"source_type":4,"start_time":1705846971650},{"elapsed_time":1103984,"interval":1,"segment":1,"source_type":4,"start_time":1705846972650},{"elapsed_time":1104984,"interval":1,"segment":1,"source_type":4,"start_time":1705846973650},{"elapsed_time":1105984,"interval":1,"segment":1,"source_type":4,"start_time":1705846974650},{"elapsed_time":1106984,"interval":1,"segment":1,"source_type":4,"start_time":1705846975650},{"elapsed_time":1107984,"interval":1,"segment":1,"source_type":4,"start_time":1705846976650},{"elapsed_time":1108984,"interval":1,"segment":1,"source_type":4,"start_time":1705846977650},{"elapsed_time":1109984,"interval":1,"segment":1,"source_type":4,"start_time":1705846978650},{"elapsed_time":1110984,"interval":1,"segment":1,"source_type":4,"start_time":1705846979650},{"elapsed_time":1111984,"interval":1,"segment":1,"source_type":4,"start_time":1705846980650},{"elapsed_time":1112984,"interval":1,"segment":1,"source_type":4,"start_time":1705846981650},{"elapsed_time":1113984,"interval":1,"segment":1,"source_type":4,"start_time":1705846982650},{"elapsed_time":1114984,"interval":1,"segment":1,"source_type":4,"start_time":1705846983650},{"elapsed_time":1115984,"interval":1,"segment":1,"source_type":4,"start_time":1705846984650},{"elapsed_time":1116984,"interval":1,"segment":1,"source_type":4,"start_time":1705846985650},{"elapsed_time":1117984,"interval":1,"segment":1,"source_type":4,"start_time":1705846986650},{"elapsed_time":1118984,"interval":1,"segment":1,"source_type":4,"start_time":1705846987650},{"elapsed_time":1119984,"interval":1,"segment":1,"source_type":4,"start_time":1705846988650},{"elapsed_time":1120984,"interval":1,"segment":1,"source_type":4,"start_time":1705846989650},{"elapsed_time":1121984,"interval":1,"segment":1,"source_type":4,"start_time":1705846990650},{"elapsed_time":1122984,"interval":1,"segment":1,"source_type":4,"start_time":1705846991650},{"elapsed_time":1123984,"interval":1,"segment":1,"source_type":4,"start_time":1705846992650},{"elapsed_time":1124984,"interval":1,"segment":1,"source_type":4,"start_time":1705846993650},{"elapsed_time":1125984,"interval":1,"segment":1,"source_type":4,"start_time":1705846994650},{"elapsed_time":1126984,"interval":1,"segment":1,"source_type":4,"start_time":1705846995650},{"elapsed_time":1127984,"interval":1,"segment":1,"source_type":4,"start_time":1705846996650},{"elapsed_time":1128984,"interval":1,"segment":1,"source_type":4,"start_time":1705846997650},{"elapsed_time":1129984,"interval":1,"segment":1,"source_type":4,"start_time":1705846998650},{"elapsed_time":1130887,"interval":1,"segment":1,"source_type":4,"start_time":1705846999553},{"elapsed_time":1132775,"interval":1,"segment":1,"source_type":4,"start_time":1705847001441},{"elapsed_time":1133775,"interval":1,"segment":1,"source_type":4,"start_time":1705847002441},{"elapsed_time":1134775,"interval":1,"segment":1,"source_type":4,"start_time":1705847003441},{"elapsed_time":1135775,"interval":1,"segment":1,"source_type":4,"start_time":1705847004441},{"elapsed_time":1136775,"interval":1,"segment":1,"source_type":4,"start_time":1705847005441},{"elapsed_time":1137775,"interval":1,"segment":1,"source_type":4,"start_time":1705847006441},{"elapsed_time":1138775,"interval":1,"segment":1,"source_type":4,"start_time":1705847007441},{"elapsed_time":1139775,"interval":1,"segment":1,"source_type":4,"start_time":1705847008441},{"elapsed_time":1140775,"interval":1,"segment":1,"source_type":4,"start_time":1705847009441},{"elapsed_time":1141775,"interval":1,"segment":1,"source_type":4,"start_time":1705847010441},{"elapsed_time":1142775,"interval":1,"segment":1,"source_type":4,"start_time":1705847011441},{"elapsed_time":1143775,"interval":1,"segment":1,"source_type":4,"start_time":1705847012441},{"elapsed_time":1144775,"interval":1,"segment":1,"source_type":4,"start_time":1705847013441},{"elapsed_time":1145775,"interval":1,"segment":1,"source_type":4,"start_time":1705847014441},{"elapsed_time":1146775,"interval":1,"segment":1,"source_type":4,"start_time":1705847015441},{"elapsed_time":1147775,"interval":1,"segment":1,"source_type":4,"start_time":1705847016441},{"elapsed_time":1148775,"interval":1,"segment":1,"source_type":4,"start_time":1705847017441},{"elapsed_time":1149775,"interval":1,"segment":1,"source_type":4,"start_time":1705847018441},{"elapsed_time":1150775,"interval":1,"segment":1,"source_type":4,"start_time":1705847019441},{"elapsed_time":1151775,"interval":1,"segment":1,"source_type":4,"start_time":1705847020441},{"elapsed_time":1152775,"interval":1,"segment":1,"source_type":4,"start_time":1705847021441},{"elapsed_time":1153775,"interval":1,"segment":1,"source_type":4,"start_time":1705847022441},{"elapsed_time":1154775,"interval":1,"segment":1,"source_type":4,"start_time":1705847023441},{"elapsed_time":1155775,"interval":1,"segment":1,"source_type":4,"start_time":1705847024441},{"elapsed_time":1156775,"interval":1,"segment":1,"source_type":4,"start_time":1705847025441},{"elapsed_time":1157775,"interval":1,"segment":1,"source_type":4,"start_time":1705847026441},{"elapsed_time":1158775,"interval":1,"segment":1,"source_type":4,"start_time":1705847027441},{"elapsed_time":1159775,"interval":1,"segment":1,"source_type":4,"start_time":1705847028441},{"elapsed_time":1160775,"interval":1,"segment":1,"source_type":4,"start_time":1705847029441},{"elapsed_time":1161775,"interval":1,"segment":1,"source_type":4,"start_time":1705847030441},{"elapsed_time":1162775,"interval":1,"segment":1,"source_type":4,"start_time":1705847031441},{"elapsed_time":1163775,"interval":1,"segment":1,"source_type":4,"start_time":1705847032441},{"elapsed_time":1164775,"interval":1,"segment":1,"source_type":4,"start_time":1705847033441},{"elapsed_time":1165775,"interval":1,"segment":1,"source_type":4,"start_time":1705847034441},{"elapsed_time":1166775,"interval":1,"segment":1,"source_type":4,"start_time":1705847035441},{"elapsed_time":1167775,"interval":1,"segment":1,"source_type":4,"start_time":1705847036441},{"elapsed_time":1168775,"interval":1,"segment":1,"source_type":4,"start_time":1705847037441},{"elapsed_time":1169775,"interval":1,"segment":1,"source_type":4,"start_time":1705847038441},{"elapsed_time":1170775,"interval":1,"segment":1,"source_type":4,"start_time":1705847039441},{"elapsed_time":1171775,"interval":1,"segment":1,"source_type":4,"start_time":1705847040441},{"elapsed_time":1172775,"interval":1,"segment":1,"source_type":4,"start_time":1705847041441},{"elapsed_time":1173775,"interval":1,"segment":1,"source_type":4,"start_time":1705847042441},{"elapsed_time":1174775,"interval":1,"segment":1,"source_type":4,"start_time":1705847043441},{"elapsed_time":1175775,"interval":1,"segment":1,"source_type":4,"start_time":1705847044441},{"elapsed_time":1176775,"interval":1,"segment":1,"source_type":4,"start_time":1705847045441},{"elapsed_time":1177775,"interval":1,"segment":1,"source_type":4,"start_time":1705847046441},{"elapsed_time":412536,"interval":1,"segment":1,"source_type":4,"start_time":1705846281202},{"elapsed_time":413536,"interval":1,"segment":1,"source_type":4,"start_time":1705846282202},{"elapsed_time":414536,"interval":1,"segment":1,"source_type":4,"start_time":1705846283202},{"elapsed_time":415536,"interval":1,"segment":1,"source_type":4,"start_time":1705846284202},{"elapsed_time":1178775,"interval":1,"segment":1,"source_type":4,"start_time":1705847047441},{"elapsed_time":1179775,"interval":1,"segment":1,"source_type":4,"start_time":1705847048441},{"elapsed_time":1180775,"interval":1,"segment":1,"source_type":4,"start_time":1705847049441},{"elapsed_time":1181775,"interval":1,"segment":1,"source_type":4,"start_time":1705847050441},{"elapsed_time":1182775,"interval":1,"segment":1,"source_type":4,"start_time":1705847051441},{"elapsed_time":1183775,"interval":1,"segment":1,"source_type":4,"start_time":1705847052441},{"elapsed_time":1184775,"interval":1,"segment":1,"source_type":4,"start_time":1705847053441},{"elapsed_time":1185775,"interval":1,"segment":1,"source_type":4,"start_time":1705847054441},{"elapsed_time":1186775,"interval":1,"segment":1,"source_type":4,"start_time":1705847055441},{"elapsed_time":1187775,"interval":1,"segment":1,"source_type":4,"start_time":1705847056441},{"elapsed_time":1188775,"interval":1,"segment":1,"source_type":4,"start_time":1705847057441},{"elapsed_time":1189775,"interval":1,"segment":1,"source_type":4,"start_time":1705847058441},{"elapsed_time":1190775,"interval":1,"segment":1,"source_type":4,"start_time":1705847059441},{"elapsed_time":1191775,"interval":1,"segment":1,"source_type":4,"start_time":1705847060441},{"elapsed_time":1192775,"interval":1,"segment":1,"source_type":4,"start_time":1705847061441},{"elapsed_time":1193775,"interval":1,"segment":1,"source_type":4,"start_time":1705847062441},{"elapsed_time":1194775,"interval":1,"segment":1,"source_type":4,"start_time":1705847063441},{"elapsed_time":1195775,"interval":1,"segment":1,"source_type":4,"start_time":1705847064441},{"elapsed_time":1196775,"interval":1,"segment":1,"source_type":4,"start_time":1705847065441},{"elapsed_time":1197775,"interval":1,"segment":1,"source_type":4,"start_time":1705847066441},{"elapsed_time":1198775,"interval":1,"segment":1,"source_type":4,"start_time":1705847067441},{"elapsed_time":1199775,"interval":1,"segment":1,"source_type":4,"start_time":1705847068441},{"elapsed_time":1200775,"interval":1,"segment":1,"source_type":4,"start_time":1705847069441},{"elapsed_time":1201775,"interval":1,"segment":1,"source_type":4,"start_time":1705847070441},{"elapsed_time":1202775,"interval":1,"segment":1,"source_type":4,"start_time":1705847071441},{"elapsed_time":1203775,"interval":1,"segment":1,"source_type":4,"start_time":1705847072441},{"elapsed_time":1204775,"interval":1,"segment":1,"source_type":4,"start_time":1705847073441},{"elapsed_time":1205775,"interval":1,"segment":1,"source_type":4,"start_time":1705847074441},{"elapsed_time":1206775,"interval":1,"segment":1,"source_type":4,"start_time":1705847075441},{"elapsed_time":604280,"interval":1,"segment":1,"source_type":4,"start_time":1705846472946},{"elapsed_time":813245,"interval":1,"segment":1,"source_type":4,"start_time":1705846681911},{"elapsed_time":1207775,"interval":1,"segment":1,"source_type":4,"start_time":1705847076441},{"elapsed_time":1208775,"interval":1,"segment":1,"source_type":4,"start_time":1705847077441},{"elapsed_time":1209775,"interval":1,"segment":1,"source_type":4,"start_time":1705847078441},{"elapsed_time":1210775,"interval":1,"segment":1,"source_type":4,"start_time":1705847079441},{"elapsed_time":1211775,"interval":1,"segment":1,"source_type":4,"start_time":1705847080441},{"elapsed_time":1212775,"interval":1,"segment":1,"source_type":4,"start_time":1705847081441},{"elapsed_time":1213775,"interval":1,"segment":1,"source_type":4,"start_time":1705847082441},{"elapsed_time":1214775,"interval":1,"segment":1,"source_type":4,"start_time":1705847083441},{"elapsed_time":1215775,"interval":1,"segment":1,"source_type":4,"start_time":1705847084441},{"elapsed_time":1216775,"interval":1,"segment":1,"source_type":4,"start_time":1705847085441},{"elapsed_time":1217775,"interval":1,"segment":1,"source_type":4,"start_time":1705847086441},{"elapsed_time":1218775,"interval":1,"segment":1,"source_type":4,"start_time":1705847087441},{"elapsed_time":1219775,"interval":1,"segment":1,"source_type":4,"start_time":1705847088441},{"elapsed_time":1220775,"interval":1,"segment":1,"source_type":4,"start_time":1705847089441},{"elapsed_time":1221775,"interval":1,"segment":1,"source_type":4,"start_time":1705847090441},{"elapsed_time":1222775,"interval":1,"segment":1,"source_type":4,"start_time":1705847091441},{"elapsed_time":1223775,"interval":1,"segment":1,"source_type":4,"start_time":1705847092441},{"elapsed_time":1224775,"interval":1,"segment":1,"source_type":4,"start_time":1705847093441},{"elapsed_time":1225775,"interval":1,"segment":1,"source_type":4,"start_time":1705847094441},{"elapsed_time":1226775,"interval":1,"segment":1,"source_type":4,"start_time":1705847095441},{"elapsed_time":1227775,"interval":1,"segment":1,"source_type":4,"start_time":1705847096441},{"elapsed_time":1228775,"interval":1,"segment":1,"source_type":4,"start_time":1705847097441},{"elapsed_time":1229775,"interval":1,"segment":1,"source_type":4,"start_time":1705847098441},{"elapsed_time":1230775,"interval":1,"segment":1,"source_type":4,"start_time":1705847099441},{"elapsed_time":1231775,"interval":1,"segment":1,"source_type":4,"start_time":1705847100441},{"elapsed_time":1232775,"interval":1,"segment":1,"source_type":4,"start_time":1705847101441},{"elapsed_time":1233775,"interval":1,"segment":1,"source_type":4,"start_time":1705847102441},{"elapsed_time":1234775,"interval":1,"segment":1,"source_type":4,"start_time":1705847103441},{"elapsed_time":1235775,"interval":1,"segment":1,"source_type":4,"start_time":1705847104441},{"elapsed_time":1236775,"interval":1,"segment":1,"source_type":4,"start_time":1705847105441},{"elapsed_time":1237775,"interval":1,"segment":1,"source_type":4,"start_time":1705847106441},{"elapsed_time":1238775,"interval":1,"segment":1,"source_type":4,"start_time":1705847107441},{"elapsed_time":1239775,"interval":1,"segment":1,"source_type":4,"start_time":1705847108441},{"elapsed_time":1240775,"interval":1,"segment":1,"source_type":4,"start_time":1705847109441},{"elapsed_time":1241775,"interval":1,"segment":1,"source_type":4,"start_time":1705847110441},{"elapsed_time":1242775,"interval":1,"segment":1,"source_type":4,"start_time":1705847111441},{"elapsed_time":1243775,"interval":1,"segment":1,"source_type":4,"start_time":1705847112441},{"elapsed_time":1244775,"interval":1,"segment":1,"source_type":4,"start_time":1705847113441},{"elapsed_time":1245775,"interval":1,"segment":1,"source_type":4,"start_time":1705847114441},{"elapsed_time":1246775,"interval":1,"segment":1,"source_type":4,"start_time":1705847115441},{"elapsed_time":1247775,"interval":1,"segment":1,"source_type":4,"start_time":1705847116441},{"elapsed_time":1248775,"interval":1,"segment":1,"source_type":4,"start_time":1705847117441},{"elapsed_time":1249775,"interval":1,"segment":1,"source_type":4,"start_time":1705847118441},{"elapsed_time":1250775,"interval":1,"segment":1,"source_type":4,"start_time":1705847119441},{"elapsed_time":1251775,"interval":1,"segment":1,"source_type":4,"start_time":1705847120441},{"elapsed_time":1252775,"interval":1,"segment":1,"source_type":4,"start_time":1705847121441},{"elapsed_time":1253775,"interval":1,"segment":1,"source_type":4,"start_time":1705847122441},{"elapsed_time":1254774,"interval":1,"segment":1,"source_type":4,"start_time":1705847123440},{"elapsed_time":1255774,"interval":1,"segment":1,"source_type":4,"start_time":1705847124440},{"elapsed_time":1256774,"interval":1,"segment":1,"source_type":4,"start_time":1705847125440},{"elapsed_time":1257774,"interval":1,"segment":1,"source_type":4,"start_time":1705847126440},{"elapsed_time":1258774,"interval":1,"segment":1,"source_type":4,"start_time":1705847127440},{"elapsed_time":1259774,"interval":1,"segment":1,"source_type":4,"start_time":1705847128440},{"elapsed_time":1260774,"interval":1,"segment":1,"source_type":4,"start_time":1705847129440},{"elapsed_time":1261774,"interval":1,"segment":1,"source_type":4,"start_time":1705847130440},{"elapsed_time":1262774,"interval":1,"segment":1,"source_type":4,"start_time":1705847131440},{"elapsed_time":1263774,"interval":1,"segment":1,"source_type":4,"start_time":1705847132440},{"elapsed_time":1264774,"interval":1,"segment":1,"source_type":4,"start_time":1705847133440},{"elapsed_time":1265774,"interval":1,"segment":1,"source_type":4,"start_time":1705847134440},{"elapsed_time":1266774,"interval":1,"segment":1,"source_type":4,"start_time":1705847135440},{"elapsed_time":1267774,"interval":1,"segment":1,"source_type":4,"start_time":1705847136440},{"elapsed_time":1268774,"interval":1,"segment":1,"source_type":4,"start_time":1705847137440},{"elapsed_time":1269774,"interval":1,"segment":1,"source_type":4,"start_time":1705847138440},{"elapsed_time":1270774,"interval":1,"segment":1,"source_type":4,"start_time":1705847139440},{"elapsed_time":1271774,"interval":1,"segment":1,"source_type":4,"start_time":1705847140440},{"elapsed_time":1272774,"interval":1,"segment":1,"source_type":4,"start_time":1705847141440},{"elapsed_time":1273774,"interval":1,"segment":1,"source_type":4,"start_time":1705847142440},{"elapsed_time":1274774,"interval":1,"segment":1,"source_type":4,"start_time":1705847143440},{"elapsed_time":1275774,"interval":1,"segment":1,"source_type":4,"start_time":1705847144440},{"elapsed_time":1276774,"interval":1,"segment":1,"source_type":4,"start_time":1705847145440},{"elapsed_time":1277774,"interval":1,"segment":1,"source_type":4,"start_time":1705847146440},{"elapsed_time":1278774,"interval":1,"segment":1,"source_type":4,"start_time":1705847147440},{"elapsed_time":1279774,"interval":1,"segment":1,"source_type":4,"start_time":1705847148440},{"elapsed_time":1280774,"interval":1,"segment":1,"source_type":4,"start_time":1705847149440},{"elapsed_time":1281767,"interval":1,"segment":1,"source_type":4,"start_time":1705847150433},{"elapsed_time":1281774,"interval":1,"segment":1,"source_type":4,"start_time":1705847150440},{"elapsed_time":1282282,"interval":1,"segment":1,"source_type":4,"start_time":1705847150948},{"elapsed_time":1283282,"interval":1,"segment":1,"source_type":4,"start_time":1705847151948},{"elapsed_time":1284282,"interval":1,"segment":1,"source_type":4,"start_time":1705847152948},{"elapsed_time":1285282,"interval":1,"segment":1,"source_type":4,"start_time":1705847153948},{"elapsed_time":1286282,"interval":1,"segment":1,"source_type":4,"start_time":1705847154948},{"elapsed_time":1287186,"interval":1,"segment":1,"source_type":4,"start_time":1705847155852},{"elapsed_time":1289578,"interval":1,"segment":1,"source_type":4,"start_time":1705847158244},{"elapsed_time":1290578,"interval":1,"segment":1,"source_type":4,"start_time":1705847159244},{"elapsed_time":1291578,"interval":1,"segment":1,"source_type":4,"start_time":1705847160244},{"elapsed_time":1292578,"interval":1,"segment":1,"source_type":4,"start_time":1705847161244},{"elapsed_time":1293578,"interval":1,"segment":1,"source_type":4,"start_time":1705847162244},{"elapsed_time":1294578,"interval":1,"segment":1,"source_type":4,"start_time":1705847163244},{"elapsed_time":1295578,"interval":1,"segment":1,"source_type":4,"start_time":1705847164244},{"elapsed_time":1296578,"interval":1,"segment":1,"source_type":4,"start_time":1705847165244},{"elapsed_time":1297578,"interval":1,"segment":1,"source_type":4,"start_time":1705847166244},{"elapsed_time":1298578,"interval":1,"segment":1,"source_type":4,"start_time":1705847167244},{"elapsed_time":1299578,"interval":1,"segment":1,"source_type":4,"start_time":1705847168244},{"elapsed_time":1300578,"interval":1,"segment":1,"source_type":4,"start_time":1705847169244},{"elapsed_time":1301578,"interval":1,"segment":1,"source_type":4,"start_time":1705847170244},{"elapsed_time":1302578,"interval":1,"segment":1,"source_type":4,"start_time":1705847171244},{"elapsed_time":1303578,"interval":1,"segment":1,"source_type":4,"start_time":1705847172244},{"elapsed_time":1304578,"interval":1,"segment":1,"source_type":4,"start_time":1705847173244},{"elapsed_time":1305578,"interval":1,"segment":1,"source_type":4,"start_time":1705847174244},{"elapsed_time":1306578,"interval":1,"segment":1,"source_type":4,"start_time":1705847175244},{"elapsed_time":1307578,"interval":1,"segment":1,"source_type":4,"start_time":1705847176244},{"elapsed_time":1308578,"interval":1,"segment":1,"source_type":4,"start_time":1705847177244},{"elapsed_time":1309578,"interval":1,"segment":1,"source_type":4,"start_time":1705847178244},{"elapsed_time":1310578,"interval":1,"segment":1,"source_type":4,"start_time":1705847179244},{"elapsed_time":1311578,"interval":1,"segment":1,"source_type":4,"start_time":1705847180244},{"elapsed_time":1312578,"interval":1,"segment":1,"source_type":4,"start_time":1705847181244},{"elapsed_time":1313578,"interval":1,"segment":1,"source_type":4,"start_time":1705847182244},{"elapsed_time":1314578,"interval":1,"segment":1,"source_type":4,"start_time":1705847183244},{"elapsed_time":1315578,"interval":1,"segment":1,"source_type":4,"start_time":1705847184244},{"elapsed_time":1316578,"interval":1,"segment":1,"source_type":4,"start_time":1705847185244},{"elapsed_time":1317578,"interval":1,"segment":1,"source_type":4,"start_time":1705847186244},{"elapsed_time":1318578,"interval":1,"segment":1,"source_type":4,"start_time":1705847187244},{"elapsed_time":1319578,"interval":1,"segment":1,"source_type":4,"start_time":1705847188244},{"elapsed_time":1320578,"interval":1,"segment":1,"source_type":4,"start_time":1705847189244},{"elapsed_time":1321578,"interval":1,"segment":1,"source_type":4,"start_time":1705847190244},{"elapsed_time":1322578,"interval":1,"segment":1,"source_type":4,"start_time":1705847191244},{"elapsed_time":1323578,"interval":1,"segment":1,"source_type":4,"start_time":1705847192244},{"elapsed_time":1324578,"interval":1,"segment":1,"source_type":4,"start_time":1705847193244},{"elapsed_time":1325578,"interval":1,"segment":1,"source_type":4,"start_time":1705847194244},{"elapsed_time":1326578,"interval":1,"segment":1,"source_type":4,"start_time":1705847195244},{"elapsed_time":1327578,"interval":1,"segment":1,"source_type":4,"start_time":1705847196244},{"elapsed_time":1328578,"interval":1,"segment":1,"source_type":4,"start_time":1705847197244},{"elapsed_time":1329578,"interval":1,"segment":1,"source_type":4,"start_time":1705847198244},{"elapsed_time":1330578,"interval":1,"segment":1,"source_type":4,"start_time":1705847199244},{"elapsed_time":1331578,"interval":1,"segment":1,"source_type":4,"start_time":1705847200244},{"elapsed_time":1332578,"interval":1,"segment":1,"source_type":4,"start_time":1705847201244},{"elapsed_time":1333578,"interval":1,"segment":1,"source_type":4,"start_time":1705847202244},{"elapsed_time":1334578,"interval":1,"segment":1,"source_type":4,"start_time":1705847203244},{"elapsed_time":1335578,"interval":1,"segment":1,"source_type":4,"start_time":1705847204244},{"elapsed_time":1336578,"interval":1,"segment":1,"source_type":4,"start_time":1705847205244},{"elapsed_time":1337578,"interval":1,"segment":1,"source_type":4,"start_time":1705847206244},{"elapsed_time":1338578,"interval":1,"segment":1,"source_type":4,"start_time":1705847207244},{"elapsed_time":1339578,"interval":1,"segment":1,"source_type":4,"start_time":1705847208244},{"elapsed_time":1340578,"interval":1,"segment":1,"source_type":4,"start_time":1705847209244},{"elapsed_time":1341578,"interval":1,"segment":1,"source_type":4,"start_time":1705847210244},{"elapsed_time":1342578,"interval":1,"segment":1,"source_type":4,"start_time":1705847211244},{"elapsed_time":1343578,"interval":1,"segment":1,"source_type":4,"start_time":1705847212244},{"elapsed_time":1344578,"interval":1,"segment":1,"source_type":4,"start_time":1705847213244},{"elapsed_time":1345578,"interval":1,"segment":1,"source_type":4,"start_time":1705847214244},{"elapsed_time":1346578,"interval":1,"segment":1,"source_type":4,"start_time":1705847215244},{"elapsed_time":1347578,"interval":1,"segment":1,"source_type":4,"start_time":1705847216244},{"elapsed_time":1348578,"interval":1,"segment":1,"source_type":4,"start_time":1705847217244},{"elapsed_time":1349578,"interval":1,"segment":1,"source_type":4,"start_time":1705847218244},{"elapsed_time":1350578,"interval":1,"segment":1,"source_type":4,"start_time":1705847219244},{"elapsed_time":1351578,"interval":1,"segment":1,"source_type":4,"start_time":1705847220244},{"elapsed_time":1352578,"interval":1,"segment":1,"source_type":4,"start_time":1705847221244},{"elapsed_time":1353578,"interval":1,"segment":1,"source_type":4,"start_time":1705847222244},{"elapsed_time":1354578,"interval":1,"segment":1,"source_type":4,"start_time":1705847223244},{"elapsed_time":1355578,"interval":1,"segment":1,"source_type":4,"start_time":1705847224244},{"elapsed_time":1356682,"interval":1,"segment":1,"source_type":4,"start_time":1705847225348},{"elapsed_time":1357929,"interval":1,"segment":1,"source_type":4,"start_time":1705847226595},{"elapsed_time":1359048,"interval":1,"segment":1,"source_type":4,"start_time":1705847227714},{"elapsed_time":1360048,"interval":1,"segment":1,"source_type":4,"start_time":1705847228714},{"elapsed_time":1361048,"interval":1,"segment":1,"source_type":4,"start_time":1705847229714},{"elapsed_time":1362048,"interval":1,"segment":1,"source_type":4,"start_time":1705847230714},{"elapsed_time":1363048,"interval":1,"segment":1,"source_type":4,"start_time":1705847231714},{"elapsed_time":1364048,"interval":1,"segment":1,"source_type":4,"start_time":1705847232714},{"elapsed_time":1365048,"interval":1,"segment":1,"source_type":4,"start_time":1705847233714},{"elapsed_time":1366048,"interval":1,"segment":1,"source_type":4,"start_time":1705847234714},{"elapsed_time":1367048,"interval":1,"segment":1,"source_type":4,"start_time":1705847235714},{"elapsed_time":1368048,"interval":1,"segment":1,"source_type":4,"start_time":1705847236714},{"elapsed_time":1369048,"interval":1,"segment":1,"source_type":4,"start_time":1705847237714},{"elapsed_time":1370048,"interval":1,"segment":1,"source_type":4,"start_time":1705847238714},{"elapsed_time":1371048,"interval":1,"segment":1,"source_type":4,"start_time":1705847239714},{"elapsed_time":1372048,"interval":1,"segment":1,"source_type":4,"start_time":1705847240714},{"elapsed_time":1374048,"interval":1,"segment":1,"source_type":4,"start_time":1705847242714},{"elapsed_time":1375048,"interval":1,"segment":1,"source_type":4,"start_time":1705847243714},{"elapsed_time":1376048,"interval":1,"segment":1,"source_type":4,"start_time":1705847244714},{"elapsed_time":1377048,"interval":1,"segment":1,"source_type":4,"start_time":1705847245714},{"elapsed_time":1378048,"interval":1,"segment":1,"source_type":4,"start_time":1705847246714},{"elapsed_time":1379048,"interval":1,"segment":1,"source_type":4,"start_time":1705847247714},{"elapsed_time":1380048,"interval":1,"segment":1,"source_type":4,"start_time":1705847248714},{"elapsed_time":1381048,"interval":1,"segment":1,"source_type":4,"start_time":1705847249714},{"elapsed_time":1382048,"interval":1,"segment":1,"source_type":4,"start_time":1705847250714},{"elapsed_time":1383048,"interval":1,"segment":1,"source_type":4,"start_time":1705847251714},{"elapsed_time":1384048,"interval":1,"segment":1,"source_type":4,"start_time":1705847252714},{"elapsed_time":1385048,"interval":1,"segment":1,"source_type":4,"start_time":1705847253714},{"elapsed_time":1386048,"interval":1,"segment":1,"source_type":4,"start_time":1705847254714},{"elapsed_time":1387048,"interval":1,"segment":1,"source_type":4,"start_time":1705847255714}]